Workbook

Sheet Model
C1: 40178 | D1: 40543 | E1: 40908 | F1: 41274 | G1: 41639 | H1: 42004 | I1: 42369 | J1: 42735 | K1: 43100 | L1: 43465 | M1: 43830 | N1: 44196 | O1: 44561 | P1: 44926 | Q1: 45291 | R1: 45747 | S1: 45838 | T1: 45930 | U1: 46022 | V1: 46022 | W1: 46112 | X1: 46203 | Y1: 46295 | Z1: 46387 | AA1: 45930 | AB1: 46752 | AC1: 47118 | AD1: 47483
C2: FY2009 | D2: FY2010 | E2: FY2011 | F2: FY2012 | G2: FY2013 | H2: FY2014 | I2: FY2015 | J2: FY2016 | K2: 2019 | L2: 2020 | M2: 2021 | N2: 2022 | O2: 2023 | P2: 2024 | Q2: 2025 | R2: 2026 | S2: 2027 | T2: 2028 | U2: 2029 | V2: 2030 | AA2: 2028 BASE | AB2: 2028 BULL | AC2: 2028 BEAR
A3: Income Statement
A4: Revenue | K4: 3090325 | L4: 3239141 | M4: 4015307 | N4: 4645714 | O4: 3569399 | P4: 3769506 | Q4: 3718971 | R4: =Q4*(1.06) -> 3942109.3 | S4: =R4*(1.06) -> 4178635.8 | T4: =S4*(1.06) -> 4429354 | U4: =T4*(1.06) -> 4695115.2 | V4: =U4*(1.06) -> 4976822.1 | AA4: =T4 -> 4429354 | AB4: =AA4*1.05 -> 4650821.7 | AC4: =AA4*0.97 -> 4296473.3
A5: Cost of goods sold | K5: 1895142 | L5: 1917378 | M5: 2131741 | N5: 2359546 | O5: 2272457 | P5: 2281011 | Q5: 2183382 | R5: =0.55*R4 -> 2168160.1 | S5: =0.55*S4 -> 2298249.7 | T5: =0.55*T4 -> 2436144.7 | U5: =0.55*U4 -> 2582313.4 | V5: =0.55*V4 -> 2737252.2 | AA5: 2235101 | AB5: =T5 -> 2436144.7 | AC5: =T5 -> 2436144.7
A6: Gross profit | K6: 1195183 | L6: 1321763 | M6: 1883566 | N6: 2286168 | O6: 1296942 | P6: 1488495 | Q6: 1535589 | R6: =R4-R5 -> 1773949.2 | S6: =S4-S5 -> 1880386.1 | T6: =T4-T5 -> 1993209.3 | U6: =U4-U5 -> 2112801.8 | V6: =V4-V5 -> 2239570 | AA6: 1828719 | AB6: =AB$4*AB42 -> 2232394.4 | AC6: =AC$4*AC42 -> 1675624.6
A8: Operating expenses:
A9: Research and development | K9: 450482 | L9: 484414 | M9: 570395 | N9: 623636 | O9: 649841 | P9: 682249 | Q9: 747709 | R9: =R47*R4 -> 0 | S9: =S47*S4 -> 793940.8 | T9: =T47*T4 -> 841577.25 | U9: =U47*U4 -> 892071.89 | V9: =V47*V4 -> 945596.2 | AA9: =AA47*AA4 -> 841577.25 | AB9: =AB47*AB4 -> 883656.12 | AC9: =AC47*AC4 -> 816329.94
A10: Selling, general and administrative | K10: 476074 | L10: 343569 | M10: 367238 | N10: 349718 | O10: 358790 | P10: 389140 | Q10: 403624 | R10: =R$4*R48 -> 394210.93 | S10: =R10*1.03 -> 406037.25 | T10: =S10*1.03 -> 418218.37 | U10: =T10*1.03 -> 430764.92 | V10: =U10*1.03 -> 443687.87 | AA10: =AA48*AA4 -> 420788.63 | AB10: =AB48*AB4 -> 372065.73 | AC10: =AC48*AC4 -> 515576.8
A12: Other operating expense | K12: 52161 | L12: 70564 | M12: 39306 | N12: 86745 | O12: 105143 | P12: 103,991 | Q12: 96160 | R12: =R6*0.05 -> 88697.458 | S12: =S6*0.05 -> 94019.306 | T12: =T6*0.05 -> 99660.464 | U12: =U6*0.05 -> 105640.09 | V12: =V6*0.05 -> 111978.5 | AA12: 91435.951 | AB12: 91435.951 | AC12: 91435.951
A13: Total operating expenses | K13: =SUM(K9:K12) -> 978717 | L13: =SUM(L9:L12) -> 898547 | M13: =SUM(M9:M12) -> 976939 | N13: =SUM(N9:N12) -> 1060099 | O13: =SUM(O9:O12) -> 1113774 | P13: =SUM(P9:P12) -> 1071389 | Q13: =SUM(Q9:Q12) -> 1247493 | R13: =SUM(R9:R12) -> 1282957 | ... V13: =SUM(V9:V12) -> 1501262.6 | AA13: 1448462.5 | AB13: =SUM(AB9:AB12) -> 1347157.8 | AC13: =SUM(AC9:AC12) -> 1423342.7
A14: Operating income | K14: =K6-K13 -> 216466 | L14: =L6-L13 -> 423216 | M14: =M6-M13 -> 906627 | N14: =N6-N13 -> 1226069 | O14: =O6-O13 -> 183168 | P14: =P6-P13 -> 417106 | Q14: =Q6-Q13 -> 288096 | R14: =R6-R13 -> 490992.15 | ... V14: =V6-V13 -> 738307.38 | AA14: 380256.54 | AB14: =AB6-AB13 -> 885236.6 | AC14: =AC6-AC13 -> 252281.92
A16: Interest expense | K16: -43963 | L16: -60392 | M16: -75198 | N16: -63326 | O16: -68463 | P16: -69245 | Q16: -78328 | R16: =Q16*1.01 -> -79111.28 | S16: =R16*1.01 -> -79902.393 | T16: =S16*1.01 -> -80701.417 | U16: =T16*1.01 -> -81508.431 | V16: =U16*1.01 -> -82323.515 | AA16: -80701.417 | AB16: -80701.417 | AC16: -80701.417
A20: Other (expense) income, net | K20: -80711 | L20: 32265 | M20: -24049 | N20: 18341 | O20: 9924 | P20: 51104 | Q20: 48700 | R20: =Q20*1.02 -> 49674 | S20: =R20*1.02 -> 50667.48 | T20: =S20*1.02 -> 51680.83 | U20: =T20*1.02 -> 52714.446 | V20: =U20*1.02 -> 53768.735 | AA20: 51680.83 | AB20: 51680.83 | AC20: 51680.83
A21: Income before income taxes | K21: 91792 | L21: 395089 | M21: 807380 | N21: 1,181,084 | O21: 124629 | P21: 73560 | Q21: 65899 | R21: =R14+R16 -> 411880.87 | S21: =S14+S16 -> 506486.36 | T21: =T14+T16 -> 553051.78 | U21: =U14+U16 -> 602816.51 | V21: =V14+V16 -> 655983.87 | AA21: 299555.12 | AB21: =AB14-AB20+AB16 -> 752854.35 | AC21: =AC14-AC20+AC16 -> 119899.67
A23: Income tax (expense) benefit | K23: 41333 | L23: -60764 | M23: -73769 | N23: (147,731) | O23: -21477 | P23: -143882 | Q23: -10284 | R23: =R21*(-0.22) -> -90613.792 | S23: =S21*(-0.22) -> -111427 | T23: =T21*(-0.22) -> -121671.39 | U23: =U21*(-0.22) -> -132619.63 | V23: =V21*(-0.22) -> -144316.45 | AA23: -65902.127 | AB23: -65902.127 | AC23: -65902.127
A24: Net income | K24: / | L24: 334325 | M24: 733611 | N24: 1033353 | O24: 103152 | P24: -70322 | Q24: 55615 | R24: =R21+R23 -> 321267.08 | S24: =S21+S23 -> 395059.36 | T24: =T21+T23 -> 431380.39 | U24: =U21+U23 -> 470196.88 | V24: =V21+V23 -> 511667.42 | AA24: 233653 | AB24: =AB21+AB23 -> 686952.22 | AC24: =AC21+AC23 -> 53997.543
A26: Operating Income as % of Revenue | AA26: =AA14/AA4 -> 0.085849211 | AB26: =AB14/AB4 -> 0.19033983 | AC26: =AC14/AC4 -> 0.058718371
A27: High Performance Analog Line | N27: 0.297 | O27: 0.273 | P27: 0.144 | Q27: 0.171 | R27: =R34/R4 -> 0.028452243 | S27: =S34/S4 -> 0.027646991 | T27: =T34/T4 -> 0.026864529 | U27: =U34/U4 -> 0.026104212 | V27: =V34/V4 -> 0.025365413 | AA27: 0.029280949 | AB27: 0.029280949 | AC27: 0.029280949
A28: Connectivity and Sensors line | N28: 0.153 | O28: -0.152 | P28: -0.204 | Q28: -0.118 | R28: =R35/R4 -> -0.013882203 | S28: =S35/S4 -> -0.012834489 | T28: =T35/T4 -> -0.011865849 | U28: =U35/U4 -> -0.010970313 | V28: =V35/V4 -> -0.010142365 | AA28: -0.012933162 | AB28: -0.012933162 | AC28: -0.012933162
A29: Advanced Cellular Group Line | N29: 0.381 | O29: 0.265 | P29: 0.264 | Q29: 0.231 | R29: =R36/R4 -> 0.16352171 | S29: =S36/S4 -> 0.16506436 | T29: =T36/T4 -> 0.16662157 | U29: =U36/U4 -> 0.16819348 | V29: =V36/V4 -> 0.16978021 | AA29: 0.18160891 | AB29: 0.18160891 | AC29: 0.18160891
A30: Mobile Products | L30: 0.298 | M30: 0.353 | N30: 0.364
A31: Infrastructure & Defense | L31: 0.173 | M31: 0.245 | N31: 0.238
A33: Gross Profit From Product Line
A34: High Performance Analog Line | N34: 210441 | O34: 198820 | P34: 82501 | Q34: 108895 | R34: =Q34*1.03 -> 112161.85 | S34: =R34*1.03 -> 115526.71 | T34: =S34*1.03 -> 118992.51 | U34: =T34*1.03 -> 122562.28 | V34: =U34*1.03 -> 126239.15 | AA34: 118992.51 | AB34: =(AB$6*AB27)*3 -> 196099.88 | AC34: =(AC$6*AC27)/3 -> 16354.626
A35: Connectivity and Sensors line | N35: 107814 | O35: -72080 | P35: -88649 | Q35: -55842 | R35: =Q35*0.98 -> -54725.16 | S35: =R35*0.98 -> -53630.657 | T35: =S35*0.98 -> -52558.044 | U35: =T35*0.98 -> -51506.883 | V35: =U35*0.98 -> -50476.745 | AA35: -52558.044 | AB35: =(AB$6*AB28)*3 -> -86615.757 | AC35: =AC$6*AC28 -> -21671.125
A36: Advanced Cellular Group Line | N36: 1233388 | O36: 627708 | P36: 729906 | Q36: 602449 | R36: =Q36*1.07 -> 644620.43 | S36: =R36*1.07 -> 689743.86 | T36: =S36*1.07 -> 738025.93 | U36: =T36*1.07 -> 789687.75 | V36: =U36*1.07 -> 844965.89 | AA36: 738025.93 | AB36: =(AB$6*AB29)*3 -> 1216268.1 | AC36: =AC$6*AC29 -> 304308.36
A37: Mobile Products | L37: 715514 | M37: 1008171
A38: Infrastructure & Defense | L38: 145295 | M38: 283507
A40: Total Product Line Revenues | L40: =SUM(L34:L38) -> 860809 | M40: =SUM(M34:M38) -> 1291678 | N40: =SUM(N34:N38) -> 1551643 | O40: =SUM(O34:O38) -> 754448 | P40: =SUM(P34:P38) -> 723758 | Q40: =SUM(Q34:Q38) -> 655502 | R40: =SUM(R34:R36) -> 702057.12 | S40: =SUM(S34:S36) -> 751639.91 | T40: =SUM(T34:T36) -> 804460.39 | U40: =SUM(U34:U36) -> 860743.14 | V40: =SUM(V34:V36) -> 920728.29 | AA40: 804460.39 | AB40: =SUM(AB34:AB36) -> 1325752.3 | AC40: =SUM(AC34:AC36) -> 298991.86
A42: Gross Margin | K42: =K6/K4 -> 0.38674994 | L42: =L6/L4 -> 0.40805973 | M42: =M6/M4 -> 0.46909639 | N42: =N6/N4 -> 0.49210261 | O42: =O6/O4 -> 0.36335024 | P42: =P6/P4 -> 0.394878 | Q42: =Q6/Q4 -> 0.41290696 | R42: =R6/R4 -> 0.45 | ... V42: =V6/V4 -> 0.45 | AA42: 0.45 | AB42: 0.48 | AC42: 0.39
A43: EBITDA Margin | L43: =(L16+L14+L158+L159)/L4 -> 0.25678259 | M43: =(M16+M14+M158+M159)/M4 -> 0.32065618 | N43: =(N16+N14+N158+N159)/N4 -> 0.32807831 | O43: =(O16+O14+O158+O159)/O4 -> 0.12706705 | P43: =(P16+P14+P158+P159)/P4 -> 0.17742219 | Q43: =(Q16+Q14+Q158+Q159)/Q4 -> 0.13622155 | R43: =(R16+R14+R158+R159)/R4 -> 0.17820005 | S43: =(S16+S14+S158+S159)/S4 -> 0.1893003 | ... V43: =(V16+V14+V158+V159)/V4 -> 0.18550266 | AA43: 0.15080338 | AB43: 0.2 | AC43: 0.09
A44: Operating Margin | K44: =K14/K4 -> 0.070046354 | L44: =L14/L4 -> 0.13065686 | M44: =M14/M4 -> 0.2257927 | N44: =N14/N4 -> 0.26391401 | O44: =O14/O4 -> 0.051316202 | P44: =P14/P4 -> 0.1106527 | Q44: =Q14/Q4 -> 0.07746659 | R44: =R14/R4 -> 0.12455062 | ... V44: =V14/V4 -> 0.14834916 | AA44: 0.093571206 | AB44: 0.14 | AC44: 0.05
A45: Net Profit Margin | L45: =L24/L4 -> 0.10321409 | M45: =M24/M4 -> 0.18270359 | N45: =1033353/4645714 -> 0.22243147 | O45: =O24/O4 -> 0.028898983 | P45: =P24/P4 -> -0.018655495 | Q45: =Q24/Q4 -> 0.014954405 | R45: =R24/R4 -> 0.08149624 | S45: =S24/S4 -> 0.094542664 | T45: =T24/T4 -> 0.097391265 | U45: =U24/U4 -> 0.10014597 | V45: =V24/V4 -> 0.10281007 | AA45: 0.057495902 | AB45: 0.11 | AC45: 0.02
A46: ROE | L46: =L24/L123 -> 0.077882854 | M46: =M24/((L123+M123)/2) -> 0.16444824 | N46: =1033353/((M123+N123)/2) -> 0.22506657 | O46: =O24/((N123+O123)/2) -> 0.024397316 | P46: =P24/((O123+P123)/2) -> -0.018855191 | Q46: =Q24/((P123+Q123)/2) -> 0.016007348 | R46: =R24/((Q123+R123)/2) -> 0.097481997 | S46: =S24/((R123+S123)/2) -> 0.12714788 | T46: =T24/((S123+T123)/2) -> 0.14735455 | U46: =U24/((T123+U123)/2) -> 0.17061252 | V46: =V24/((U123+V123)/2) -> 0.19744023 | AA46: 0.079813158 | AB46: 0.12 | AC46: 0.03
A47: R&D Intensity | K47: =K9/K4 -> 0.14577172 | L47: =L9/L4 -> 0.14955014 | M47: =M9/M4 -> 0.14205514 | N47: =N9/N4 -> 0.134239 | O47: =O9/O4 -> 0.18205894 | P47: =P9/P4 -> 0.18099162 | Q47: =Q9/Q4 -> 0.20105266 | R47: =R9/R4 -> 0.20294938 | S47: 0.19 | T47: 0.19 | U47: 0.19 | V47: 0.19 | AA47: 0.19 | AB47: 0.19 | AC47: 0.19
A48: SG&A Margin | R48: 0.1 | S48: 0.1 | T48: 0.095 | U48: 0.09 | V48: 0.09 | AA48: 0.095 | AB48: 0.08 | AC48: 0.12
A50: Free Cash Flow Margin | L50: =(L176-(L88-K88))/L4 -> -0.096802516 | M50: =(M176-(M88-L88))/M4 -> 0.32252204 | N50: =(N176-(N88-M88))/N4 -> 0.22852957 | O50: =(O176-(O88-N88))/O4 -> 0.26531525 | P50: =(P176-(P88-O88))/P4 -> 0.29500232 | Q50: =(Q176-(Q88-P88))/Q4 -> 0.18588179 | R50: =(R176-(R88-Q88))/R4 -> 0.46533258 | S50: =(S176-(S88-R88))/S4 -> -0.01416107 | ... V50: =(V176-(V88-U88))/V4 -> 0.4090332 | AA50: 0.4479158 | AB50: 0.49 | AC50: 0.4
A52: EBITDA | L52: =(L16+L14+L158+L159) -> 831755 | M52: =(M16+M14+M158+M159) -> 1287533 | N52: =(N16+N14+N158+N159) -> 1524158 | O52: =(O16+O14+O158+O159) -> 453553 | P52: =(P16+P14+P158+P159) -> 668794 | Q52: =(Q16+Q14+Q158+Q159) -> 506604 | R52: =(R16+R14+R158+R159) -> 702484.07 | S52: =(S16+S14+S158+S159) -> 791017.02 | ... V52: =(V16+V14+V158+V159) -> 923213.74 | AA52: =AA43*AA$4 -> 667961.56 | AB52: =AB$4*AB43 -> 930164.33 | AC52: =AC$4*AC43 -> 386682.6
A53: Effective Tax Rate | R53: 0.22 | S53: 0.22 | T53: 0.22 | U53: 0.22 | V53: 0.22 | AA53: 0.22 | AB53: 0.22 | AC53: 0.22
N57: 9.26 | O57: 1 | P57: -0.72 | Q57: 0.6 | R57: 1.55 | S57: 3.2 | T57: 4.15 | U57: 4.65 | V57: 5.1 | AA57: 4.15 | AB57: 6.2 | AC57: 1.2
A58: Earnings Per Share - WAB | P58: -0.72 | Q58: 0.59 | R58: 1.55 | S58: 3.2 | T58: 4.1 | U58: 4.6 | V58: 5.05 | AA58: 4.1 | AB58: 6.1 | AC58: 1.1
A59: Earnings Per Share - WAD | P59: 5.38 | Q59: 5.82 | R59: 3.14 | S59: 8.7 | T59: 10.3 | U59: 11.5 | V59: 12.8 | AA59: 10.3 | AB59: 12.3 | AC59: 5.3
A60: Adjusted Earnings Per Share - WAD
A62: Shares Outstanding - WAB | P62: 97557 | Q62: 93750 | R62: 92800 | S62: 91500 | T62: 90000 | U62: 88500 | V62: 87000 | AA62: 90000 | AB62: =90000*0.97 -> 87300 | AC62: =90000*1.01 -> 90900
A63: Shares Outstanding - WAD | P63: 97,557 | Q63: 94920 | R63: 93800 | S63: 92300 | T63: 91000 | U63: 89500 | V63: 88000 | AA63: 91000 | AB63: =91000*0.97 -> 88270 | AC63: =91000*1.01 -> 91910
A64: Adjusted Shares Outstanding - WAD | P64: 98223 | Q64: 95300 | R64: 93,800 | S64: 92300 | T64: 91000 | U64: 89500 | V64: 88000 | AA64: 91000 | AB64: =91000*0.97 -> 88270 | AC64: =91000*1.01 -> 91910
A75: Balance Sheet
A76: Current Assets
A77: Cash and cash equivalents
L78: 714939 | M78: 1397880 | N78: 972592 | O78: 808757 | P78: 1029258 | Q78: 1021176 | R78: =Q78*1.02 -> 1041599.5 | S78: =R78*1.02 -> 1062431.5 | T78: =S78*1.02 -> 1083680.1 | U78: =T78*1.02 -> 1105353.7 | V78: =U78*1.02 -> 1127460.8 | AA78: 1083680.1 | AB78: =AA78*1.04 -> 1127027.3 | AC78: =AA78*0.95 -> 1029496.1
A79: Accounts receivable, net of allowance of $331 and $55 as of April 3, 2021 and March 28, 2020, respectively | L79: 367172 | M79: 457431 | N79: 568850 | O79: 304519 | P79: 412960 | Q79: 386719 | R79: =Q79*1.01 -> 390586.19 | S79: =R79*1.01 -> 394492.05 | T79: =S79*1.01 -> 398436.97 | U79: =T79*1.01 -> 402421.34 | V79: =U79*1.01 -> 406445.56 | AA79: 398436.97 | AB79: =AB$4*AB128 -> 455989.51 | AC79: =AC$4*AC128 -> 421247.45
A80: Inventories | L80: 517198 | M80: 507787 | N80: 755748 | O80: 796596 | P80: 710555 | Q80: 640992 | R80: =Q80*0.99 -> 634582.08 | S80: =R80*0.99 -> 628236.26 | T80: =S80*0.99 -> 621953.9 | U80: =T80*0.99 -> 615734.36 | V80: =U80*0.99 -> 609577.01 | AA80: 621953.9 | AB80: 621953.9 | AC80: 621953.9
A81: Prepaid expenses | L81: 37872 | M81: 41572 | N81: 49839 | O81: 46684 | P81: 40563 | Q81: 32808 | R81: =Q81*0.9 -> 29527.2 | S81: =R81*0.9 -> 26574.48 | T81: =S81*0.9 -> 23917.032 | U81: =T81*0.9 -> 21525.329 | V81: =U81*0.9 -> 19372.796 | AA81: 23917.032 | AB81: 23917.032 | AC81: 23917.032
A82: Assets of disposal group held for sale | P82: 159278
A83: Other receivables | L83: 15016 | M83: 27324 | N83: 32151 | O83: 26535 | P83: 14427 | Q83: 11023 | R83: =Q83*0.95 -> 10471.85 | S83: =R83*0.95 -> 9948.2575 | T83: =S83*0.95 -> 9450.8446 | U83: =T83*0.95 -> 8978.3024 | V83: =U83*0.95 -> 8529.3873 | AA83: 9450.8446 | AB83: 9450.8446 | AC83: 9450.8446
A84: Other current assets | L84: 38305 | M84: 51810 | N84: 70685 | O84: 46703 | P84: 78993 | Q84: 74557 | R84: =Q84*0.975 -> 72693.075 | S84: =R84*0.975 -> 70875.748 | T84: =S84*0.975 -> 69103.854 | U84: =T84*0.975 -> 67376.258 | V84: =U84*0.975 -> 65691.852 | AA84: 69103.854 | AB84: 69103.854 | AC84: 69103.854
A85: Total Current Assets | L85: 1690502 | M85: 2483804 | N85: 2449865 | O85: 2029794 | P85: =SUM(P77:P84) -> 2446034 | Q85: =SUM(Q77:Q84) -> 2167275 | R85: =SUM(R78:R84) -> 2179459.9 | S85: =SUM(S78:S84) -> 2192558.3 | T85: =SUM(T78:T84) -> 2206542.7 | U85: =SUM(U78:U84) -> 2221389.3 | V85: =SUM(V78:V84) -> 2237077.4 | AA85: 2206542.7 | AB85: =SUM(AB77:AB84) -> 2307442.5 | AC85: =SUM(AC77:AC84) -> 2175169.2
A87: Non-Current Assets
A88: Property and equipment, net | L88: 1259203 | M88: 1266031 | N88: 1253591 | O88: 1149806 | P88: 870982 | Q88: 801895 | R88: =Q88*0.9 -> 721705.5 | S88: =R88*0.9 -> 649534.95 | T88: =S88*0.9 -> 584581.46 | U88: =T88*0.9 -> 526123.31 | V88: =U88*0.9 -> 473510.98 | AA88: 584581.46 | AB88: 584581.46 | AC88: 584581.46
A89: Goodwill | L89: 2614274 | M89: 2642708 | N89: 2775634 | O89: 2760813 | P89: 2534601 | Q89: 2389741 | R89: =Q89*0.97 -> 2318048.8 | S89: =R89*0.97 -> 2248507.3 | T89: =S89*0.97 -> 2181052.1 | U89: =T89*0.97 -> 2115620.5 | V89: =U89*0.97 -> 2052151.9 | AA89: 2181052.1 | AB89: 2181052.1 | AC89: 2181052.1
A90: Intangible assets, net | L90: 808892 | M90: 611155 | N90: 674786 | O90: 537703 | P90: 509383 | Q90: 273478 | R90: =Q90*0.95 -> 259804.1 | S90: =R90*0.95 -> 246813.89 | T90: =S90*0.95 -> 234473.2 | U90: =T90*0.95 -> 222749.54 | V90: =U90*0.95 -> 211612.06 | AA90: 234473.2 | AB90: 234473.2 | AC90: 234473.2
A91: Long-term investments | L91: 22515 | M91: 35370 | N91: 31086 | O91: 20406 | P91: 23252 | Q91: 23433 | R91: =Q91*1.01 -> 23667.33 | S91: =R91*1.01 -> 23904.003 | T91: =S91*1.01 -> 24143.043 | U91: =T91*1.01 -> 24384.474 | V91: =U91*1.01 -> 24628.319 | AA91: 24143.043 | AB91: 24143.043 | AC91: 24143.043
A92: Other non-current assets | L92: 165296 | M92: 182402 | N92: 324110 | O92: 193381 | P92: 170383 | Q92: 277309 | R92: =Q92*1.04 -> 288401.36 | S92: =R92*1.04 -> 299937.41 | T92: =S92*1.04 -> 311934.91 | U92: =T92*1.04 -> 324412.31 | V92: =U92*1.04 -> 337388.8 | AA92: 311934.91 | AB92: 311934.91 | AC92: 311934.91
A93: Total Non-Current Assets | L93: =SUM(L88:L92) -> 4870180 | M93: =SUM(M88:M92) -> 4737666 | N93: =SUM(N88:N92) -> 5059207 | O93: =SUM(O88:O92) -> 4662109 | P93: =SUM(P88:P92) -> 4108601 | Q93: =SUM(Q88:Q92) -> 3765856 | R93: =SUM(R88:R92) -> 3611627.1 | S93: =SUM(S88:S92) -> 3468697.6 | ... V93: =SUM(V88:V92) -> 3099292.1 | AA93: 3336184.7 | AB93: 3336184.7 | AC93: 3336184.7
A94: Total Assets | L94: 6560682 | M94: 7221470 | N94: =N85+N93 -> 7509072 | O94: =+O93+O85 -> 6691903 | P94: =+P93+P85 -> 6554635 | Q94: =+Q93+Q85 -> 5933131 | R94: =R93+R85 -> 5791087 | S94: =S93+S85 -> 5661255.9 | T94: =T93+T85 -> 5542727.4 | U94: =U93+U85 -> 5434679.5 | V94: =V93+V85 -> 5336369.5 | AA94: 5542727.4 | AB94: 5542727.4 | AC94: 5542727.4
A96: Current Liabilities
A97: Current liabilities:
A98: Accounts payable | L98: 246954 | M98: 313868 | N98: 327915 | O98: 210701 | P98: 252993 | Q98: 260663 | R98: =Q98*0.98 -> 255449.74 | S98: =R98*0.98 -> 250340.75 | T98: =S98*0.98 -> 245333.93 | U98: =T98*0.98 -> 240427.25 | V98: =U98*0.98 -> 235618.71 | AA98: 245333.93 | AB98: =AB$4*AB129 -> 280771.38 | AC98: =AC$4*AC129 -> 259379.28
A99: Accrued liabilities | L99: 217801 | M99: 255060 | N99: 240186 | O99: 222463 | P99: 336767 | Q99: 287981 | R99: =Q99*0.99 -> 285101.19 | S99: =R99*0.99 -> 282250.18 | T99: =S99*0.99 -> 279427.68 | U99: =T99*0.99 -> 276633.4 | V99: =U99*0.99 -> 273867.07 | AA99: 279427.68 | AB99: 279427.68 | AC99: 279427.68
A100: Current portion of long-term debt | L100: 6893 | M100: 5092 | N100: N/A | O100: N/A | P100: 438740 | Q100: —
A101: Other current liabilities | L101: 67355 | M101: 107561 | N101: 107026 | O101: 122599 | P101: 113215 | Q101: 234538 | R101: =Q101*0.98 -> 229847.24 | S101: =R101*0.98 -> 225250.3 | T101: =S101*0.98 -> 220745.29 | U101: =T101*0.98 -> 216330.38 | V101: =U101*0.98 -> 212003.78 | AA101: 220745.29 | AB101: 220745.29 | AC101: 220745.29
P102: 88372 | Q102: —
A103: Total Current Liabilities | L103: 539003 | M103: 681581 | N103: 675127 | O103: 555763 | P103: =SUM(P98:P102) -> 1230087 | Q103: =SUM(Q97:Q102) -> 783182 | R103: =SUM(R98:R101) -> 770398.17 | S103: =SUM(S98:S101) -> 757841.22 | T103: =SUM(T98:T101) -> 745506.9 | U103: =SUM(U98:U101) -> 733391.03 | V103: =SUM(V98:V101) -> 721489.55 | AA103: 745506.9 | AB103: =SUM(AB98:AB102) -> 780944.35 | AC103: =SUM(AC98:AC102) -> 759552.24
A104: Long-term debt | L104: 1567231 | M104: 1742550 | N104: 2047098 | O104: 2048073 | P104: 1549272 | Q104: 1549215 | R104: 1549215 | S104: 1549215 | T104: 1549215 | U104: 1549215 | V104: 1549215 | W104: 1549215 | AA104: 1549215 | AB104: 1549215 | AC104: 1549215
A106: Other long-term liabilities | L106: 161783 | M106: 167914 | N106: 233629 | O106: 185273 | P106: 218904 | Q106: 208422 | R106: =Q106*1.01 -> 210506.22 | S106: =R106*1.01 -> 212611.28 | T106: =S106*1.01 -> 214737.4 | U106: =T106*1.01 -> 216884.77 | V106: =U106*1.01 -> 219053.62 | AA106: 214737.4 | AB106: 214737.4 | AC106: 214737.4
A113: Total Non-Current liabilities | L113: =SUM(L104:L112) -> 1729014 | M113: =SUM(M104:M112) -> 1910464 | N113: =SUM(N104:N112) -> 2280727 | O113: =SUM(O104:O112) -> 2233346 | P113: =SUM(P104:P112) -> 1768176 | Q113: =SUM(Q104:Q112) -> 1757637 | R113: =SUM(R104:R106) -> 1759721.2 | S113: =SUM(S104:S106) -> 1761826.3 | T113: =SUM(T104:T106) -> 1763952.4 | U113: =SUM(U104:U106) -> 1766099.8 | V113: =SUM(V104:V106) -> 1768268.6 | AA113: 1957393.6
A114: Total Liabilities | L114: =+L113+L103 -> 2268017 | M114: =+M113+M103 -> 2592045 | N114: =+N113+N103 -> 2955854 | O114: =+O113+O103 -> 2789109 | P114: =+P113+P103 -> 2998263 | Q114: =+Q113+Q103 -> 2540819 | R114: =R103+R113 -> 2530119.4 | S114: =S103+S113 -> 2519667.5 | T114: =T103+T113 -> 2509459.3 | U114: =U103+U113 -> 2499490.8 | V114: =V103+V113 -> 2489758.2 | AA114: 2702900.5
A116: Shareholders' Equity
A117: Commitments and contingent liabilities
A118: Stockholders’ equity:
A119: Preferred stock, $.0001 par value; 5,000 shares authorized; no shares issued and outstanding | L119: — | M119: — | N119: — | O119: — | P119: — | Q119: —
A120: Common stock and additional paid-in capital, $.0001 par value; 405,000 shares authorized; 112,557 and 114,625 shares issued and outstanding at April 3, 2021 and March 28, 2020, respectively | L120: 4290377 | M120: 4244740 | N120: 4035849 | O120: 3821474 | P120: 3651067 | Q120: 3431308 | R120: =Q120*0.94 -> 3225429.5 | S120: =R120*0.94 -> 3031903.7 | T120: =S120*0.94 -> 2849989.5 | U120: =T120*0.94 -> 2678990.2 | V120: =U120*0.94 -> 2518250.7 | AA120: 2849989.5
A121: Accumulated other comprehensive income | L121: 2288 | M121: 29649 | N121: 5232 | O121: -3175 | P121: -5097 | Q121: -5013 | R121: 5513.5 | S121: 13934.9 | T121: 19277.1 | U121: 21313.1 | V121: 19850.2 | AA121: 19277.1
A122: Retained earnings | L122: — | M122: 355036 | N122: 512137 | O122: 84495 | P122: -89598 | Q122: -33983 | R122: =Q122*0.94 -> -31944.02 | S122: =R122*0.96 -> -30666.259 | T122: =S122*0.96 -> -29439.609 | U122: =T122*0.96 -> -28262.024 | V122: =U122*0.96 -> -27131.543 | AA122: -29439.609
A123: Total SE | L123: =SUM(L118:L122) -> 4292665 | M123: =SUM(M118:M122) -> 4629425 | N123: =SUM(N118:N122) -> 4553218 | O123: =SUM(O118:O122) -> 3902794 | P123: =SUM(P118:P122) -> 3556372 | Q123: =SUM(Q118:Q122) -> 3392312 | R123: =SUM(R120:R122) -> 3198999 | S123: =SUM(S120:S122) -> 3015172.4 | T123: =SUM(T120:T122) -> 2839827 | U123: =SUM(U120:U122) -> 2672041.2 | V123: =SUM(V120:V122) -> 2510969.4 | AA123: 2839827
A125: Total Liabilities & SE | L125: =+L124+L123+L114 -> 6560682 | M125: =+M124+M123+M114 -> 7221470 | N125: =+N124+N123+N114 -> 7509072 | O125: =+O124+O123+O114 -> 6691903 | P125: =+P124+P123+P114 -> 6554635 | Q125: =+Q124+Q123+Q114 -> 5933131 | R125: =R123+R114 -> 5729118.4 | S125: =S123+S114 -> 5534839.9 | T125: =T123+T114 -> 5349286.3 | U125: =U123+U114 -> 5171532 | V125: =V123+V114 -> 5000727.6 | AA125: 5542727.5
A128: Receivables as % of Revenue | L128: =L79/L4 -> 0.11335474 | M128: =M79/M4 -> 0.1139218 | N128: =N79/N4 -> 0.12244619 | O128: =O79/O4 -> 0.085313802 | P128: =P79/P4 -> 0.10955282 | Q128: =Q79/Q4 -> 0.10398548 | R128: =R79/R4 -> 0.099080508 | S128: =S79/S4 -> 0.0944069 | ... V128: =V79/V4 -> 0.081667688 | AA128: 0.098044936 | AB128: 0.098044936 | AC128: 0.098044936
A129: Payables as % of Revenue | L129: =L98/L4 -> 0.076240584 | M129: =M98/M4 -> 0.078167871 | N129: =N98/N4 -> 0.070584414 | O129: =O98/O4 -> 0.059029825 | P129: =P98/P4 -> 0.067115691 | Q129: =Q98/Q4 -> 0.070090087 | R129: =R98/R4 -> 0.064800269 | S129: =S98/S4 -> 0.059909683 | ... V129: =V98/V4 -> 0.047343204 | AA129: 0.060370274 | AB129: 0.060370274 | AC129: 0.060370274
A130: Depreciation as % of Revenue | L130: =L158/L4 -> 0.068423079 | M130: =M158/M4 -> 0.050607836 | N130: =N158/N4 -> 0.045407229 | O130: =O158/O4 -> 0.057831304 | P130: =P158/P4 -> 0.051209628 | Q130: =Q158/Q4 -> 0.043889022 | R130: =R158/R4 -> 0.040162596 | S130: =S158/S4 -> 0.036752564 | ... V130: =V158/V4 -> 0.028163411 | AA130: 0.036657212 | AB130: 0.036657212 | AC130: 0.036657212
A131: Amortization as % of Revenue | L131: =L158/L4 -> 0.068423079 | M131: =M158/M4 -> 0.050607836 | N131: =N158/N4 -> 0.045407229 | O131: =O158/O4 -> 0.057831304 | P131: =P158/P4 -> 0.051209628 | Q131: =Q158/Q4 -> 0.043889022 | R131: =R158/R4 -> 0.040162596 | S131: =S158/S4 -> 0.036752564 | ... V131: =V158/V4 -> 0.028163411 | AA131: 0.036657212 | AB131: 0.036657212 | AC131: 0.036657212
A132: Capex as % of Revenue | L132: =(L179-L181)/L4 -> -0.051264826 | M132: =(M179-M181)/M4 -> -0.040869602 | N132: =(N179-N181)/N4 -> -0.045949019 | O132: =(O179-O181)/O4 -> -0.044532147 | P132: =(P179-P181)/P4 -> -0.01174053 | Q132: =(Q179-Q181)/Q4 -> -0.036786789 | R132: =(R179-R181)/R4 -> -0.034704518 | S132: =(S179-S181)/S4 -> -0.032740111 | ... V132: =(V179-V181)/V4 -> -0.027489228 | AA132: -0.033665123 | AB132: -0.033665123 | AC132: -0.033665123
A154: Cash Flow Statement
A155: CFO
A156: Net income | L156: 334325 | M156: 733611 | N156: 1033353 | O156: 103152 | P156: -70322 | Q156: 55615 | R156: =R24 -> 321267.08 | S156: =S24 -> 395059.36 | T156: =T24 -> 431380.39 | U156: =U24 -> 470196.88 | V156: =V24 -> 511667.42 | AA156: 233653 | AB156: =AB24 -> 686952.22 | AC156: =AC24 -> 53997.543
A157: Adjustments to reconcile net income to net cash provided by operating activities:
A158: Depreciation | L158: 221632 | M158: 203206 | N158: 210949 | O158: 206423 | P158: 193035 | Q158: 163222 | R158: =Q158*0.97 -> 158325.34 | S158: =R158*0.97 -> 153575.58 | T158: =S158*0.97 -> 148968.31 | U158: =T158*0.97 -> 144499.26 | V158: =U158*0.97 -> 140164.29 | AA158: 148968.31 | AB158: =AB$4*AB130 -> 170486.16 | AC158: =AC$4*AC130 -> 157496.73
A159: Intangible assets amortization | L159: 247299 | M159: 252898 | N159: 150466 | O159: 132425 | P159: 127898 | Q159: 133614 | R159: =Q159*0.99 -> 132277.86 | S159: =R159*0.99 -> 130955.08 | T159: =S159*0.99 -> 129645.53 | U159: =T159*0.99 -> 128349.08 | V159: =U159*0.99 -> 127065.58 | AA159: 129645.53 | AB159: =AB$4*AB131 -> 170486.16 | AC159: =AC$4*AC131 -> 157496.73
A160: Loss on debt extinguishment | L160: — | M160: 61991 | N160: 744 | O160: — | Q160: -84737
A161: Deferred income taxes | L161: -11099 | M161: -18136 | N161: 31875 | O161: -66145 | P161: 19405
...

Sheet DCF
A1: Discounted Cash Flow Analysis (Note: Select the entire sheet using Ctrl + A and paste it into your financial model.)
B3: Date | C3: 44712 | D3: 45077 | E3: 45443 | F3: 45808 | G3: 46173 | H3: 46538 | I3: 46904 | J3: 47269 | K3: 47634
B4: Year | C4: =Model!N2 -> 2022 | D4: =Model!O2 -> 2023 | E4: =Model!P2 -> 2024 | F4: =Model!Q2 -> 2025 | G4: =Model!R2 -> 2026 | H4: =Model!S2 -> 2027 | I4: =Model!T2 -> 2028 | J4: =Model!U2 -> 2029 | K4: =Model!V2 -> 2030
B5: Revenue | C5: =Model!N4 -> 4645714 | D5: =Model!O4 -> 3569399 | E5: =Model!P4 -> 3769506 | F5: =Model!Q4 -> 3718971 | G5: =Model!R4 -> 3942109.3 | H5: =Model!S4 -> 4178635.8 | I5: =Model!T4 -> 4429354 | J5: =Model!U4 -> 4695115.2 | K5: =Model!V4 -> 4976822.1
B6: Growth | D6: =D5/C5-1 -> -0.23167913 | E6: =E5/D5-1 -> 0.056061819 | F6: =F5/E5-1 -> -0.013406266 | G6: =G5/F5-1 -> 0.06 | H6: =H5/G5-1 -> 0.06 | I6: =I5/H5-1 -> 0.06 | J6: =J5/I5-1 -> 0.06 | K6: =K5/J5-1 -> 0.06
B8: Adj. EBITDA | C8: =Model!N52 -> 1524158 | D8: =Model!O52 -> 453553 | E8: =Model!P52 -> 668794 | F8: =Model!Q52 -> 506604 | G8: =Model!R52 -> 702484.07 | H8: =Model!S52 -> 791017.02 | I8: =Model!T52 -> 831665.62 | J8: =Model!U52 -> 875664.85 | K8: =Model!V52 -> 923213.74
B9: Margin | C9: =C8/C5 -> 0.32807831 | D9: =D8/D5 -> 0.12706705 | E9: =E8/E5 -> 0.17742219 | F9: =F8/F5 -> 0.13622155 | G9: =G8/G5 -> 0.17820005 | H9: =H8/H5 -> 0.1893003 | I9: =I8/I5 -> 0.18776228 | J9: =J8/J5 -> 0.18650551 | K9: =K8/K5 -> 0.18550266
B11: EBIT | C11: =Model!N14 -> 1226069 | D11: =Model!O14 -> 183168 | E11: =Model!P14 -> 417106 | F11: =Model!Q14 -> 288096 | G11: =Model!R14 -> 490992.15 | H11: =Model!S14 -> 586388.75 | I11: =Model!T14 -> 633753.2 | J11: =Model!U14 -> 684324.94 | K11: =Model!V14 -> 738307.38
B12: Margin | C12: =C11/C5 -> 0.26391401 | D12: =D11/D5 -> 0.051316202 | E12: =E11/E5 -> 0.1106527 | F12: =F11/F5 -> 0.07746659 | G12: =G11/G5 -> 0.12455062 | H12: =H11/H5 -> 0.14033019 | I12: =I11/I5 -> 0.14308028 | J12: =J11/J5 -> 0.14575253 | K12: =K11/K5 -> 0.14834916
B14: Tax | C14: =C11*G15 -> 269735.18 | D14: =D11*H15 -> 40296.96 | E14: =E11*I15 -> 91763.32 | F14: =F11*J15 -> 63381.12 | G14: =G11*(G15) -> 108018.27 | H14: =H11*(H15) -> 129005.53 | I14: =I11*(I15) -> 139425.7 | J14: =J11*(J15) -> 150551.49 | K14: =K11*(K15) -> 162427.62
B15: Tax rate | G15: =Model!R53 -> 0.22 | H15: =Model!S53 -> 0.22 | I15: =Model!T53 -> 0.22 | J15: =Model!U53 -> 0.22 | K15: =Model!V53 -> 0.22
B17: NOPAT | C17: =C11-C14 -> 956333.82 | D17: =D11-D14 -> 142871.04 | E17: =E11-E14 -> 325342.68 | F17: =F11-F14 -> 224714.88 | G17: =G11-G14 -> 382973.88 | H17: =H11-H14 -> 457383.23 | I17: =I11-I14 -> 494327.49 | J17: =J11-J14 -> 533773.45 | K17: =K11-K14 -> 575879.76
B19: NWC | C19: =(Model!N85-Model!N103)-(Model!M85-Model!M103) -> -27485 | D19: =(Model!O85-Model!O103)-(Model!N85-Model!N103) -> -300707 | E19: =(Model!P85-Model!P103)-(Model!O85-Model!O103) -> -258084 | F19: =(Model!Q85-Model!Q103)-(Model!P85-Model!P103) -> 168146 | G19: =(Model!R85-Model!R103)-(Model!Q85-Model!Q103) -> 24968.745 | H19: =(Model!S85-Model!S103)-(Model!R85-Model!R103) -> 25655.344 | I19: =(Model!T85-Model!T103)-(Model!S85-Model!S103) -> 26318.756 | J19: =(Model!U85-Model!U103)-(Model!T85-Model!T103) -> 26962.453 | K19: =(Model!V85-Model!V103)-(Model!U85-Model!U103) -> 27589.577
B21: D&A | C21: =Model!N158+Model!N159 -> 361415 | D21: =Model!O158+Model!O159 -> 338848 | E21: =Model!P158+Model!P159 -> 320933 | F21: =Model!Q158+Model!Q159 -> 296836 | G21: =Model!R158+Model!R159 -> 290603.2 | H21: =Model!S158+Model!S159 -> 284530.66 | I21: =Model!T158+Model!T159 -> 278613.84 | J21: =Model!U158+Model!U159 -> 272848.34 | K21: =Model!V158+Model!V159 -> 267229.87
B23: Capex | C23: =Model!N179-Model!N181 -> -213466 | D23: =Model!O179-Model!O181 -> -158953 | E23: =Model!P179-Model!P181 -> -44256 | F23: =Model!Q179-Model!Q181 -> -136809 | G23: =Model!R179-Model!R181 -> -136809 | H23: =Model!S179-Model!S181 -> -136809 | I23: =Model!T179-Model!T181 -> -136809 | J23: =Model!U179-Model!U181 -> -136809 | K23: =Model!V179-Model!V181 -> -136809
B25: Unlevered FCF | C25: =(C17+C19+C21+C23) -> 1076797.8 | D25: =(D17+D19+D21+D23) -> 22059.04 | E25: =(E17+E19+E21+E23) -> 343935.68 | F25: =(F17+F19+F21+F23) -> 552887.88 | G25: =G17+G19+G21+G23 -> 561736.82 | H25: =H17+H19+H21+H23 -> 630760.23 | I25: =I17+I19+I21+I23 -> 662451.09 | J25: =J17+J19+J21+J23 -> 696775.24 | K25: =K17+K19+K21+K23 -> 733890.2
B27: Present Value of Unlevered FCF | G27: =G25/(1+$C$31)^G28 -> 515190.85 | H27: =H25/(1+$C$31)^H28 -> 583053.38 | I27: =I25/(1+$C$31)^I28 -> 616733.13 | J27: =J25/(1+$C$31)^J28 -> 652911.56 | K27: =K25/(1+$C$31)^K28 -> 691759.59
B28: Discount factor | G28: =1/(1+$C$31)^1 -> 0.90925623 | H28: =1/(1+$C$31)^2 -> 0.82674689 | I28: =1/(1+$C$31)^3 -> 0.75172476 | J28: =1/(1+$C$31)^4 -> 0.68351042 | K28: =1/(1+$C$31)^5 -> 0.62148611
B29: 2027 FCF | C29: =I25 -> 662451.09
B30: 2028 FCF | C30: =J25 -> 696775.24
B31: WACC | C31: 0.0998
B32: Long term growth rate (g) | C32: 0.02
B33: Terminal Value | C33: =K25*(1+C32)/(C31-C32) -> 9380551.5
B34: Present Value of Terminal Value | C34: =C33/(1+C31)^K28 -> 8842039.9
B35: Present Value of Forecast Period CFs | C35: =SUM(G27:K27) -> 2820700.4
B36: Enterprise value | C36: =SUM(C34:C35) -> 10693809
B37: Implied TV exit EBITDA multiple | C37: =C36/K8 -> 13.039491
B38: Cash | C38: =Model!Q78 -> 1021176
B39: Total Debt | C39: =Model!Q104 -> 1549215
B40: Net debt | C40: =C39-C38 -> 528039
B41: Equity Value | C41: =C36-C40 -> 10165770
B42: Shares Outstanding | C42: =Model!Q63 -> 94920
B43: Price per share | C43: =C41/C42 -> 107.09829
B44: Upside/Downside | C44: =C43/Valuation!B2-1 -> 0.0062791853

Sheet Relative Valuation
A2: Comparable Analysis
D4: USD | I4: 1Yr | J4: EV / | M4: EBIT
C5: Last | D5: Market | E5: USD | F5: % Chg | G5: % Chg | H5: USD | I5: Sales | J5: EBITDA | K5: P/E | M5: Margin | N5: Dvd
A6: Ticker | B6: Name | C6: Price | D6: Cap | E6: EV | F6: 1Yr | G6: YTD | H6: Sales | I6: GR | J6: Crnt Yr | K6: Crnt Yr | L6: NY | M6: T12M | N6: Yield
A8: AVGO | B8: Broadcom Inc | C8: 412.14 | D8: 1960 | E8: 2010 | F8: 0.7965 | G8: 0.1966 | H8: 68.28 | I8: 0.0643 | J8: 53.92 | K8: 36.5 | L8: 22.7 | M8: 0.4184 | N8: 0.0063
A9: QCOM | B9: Qualcomm Inc | C9: 238.16 | D9: 251 | E9: 256 | F9: 0.6161 | G9: 0.3923 | H9: 44.28 | I9: 0.1366 | J9: 20.7 | K9: 22.05 | L9: 22.38 | M9: 0.3009 | N9: 0.0155
A10: ADI | B10: Analog Devices Inc | C10: 397.07 | D10: 194 | E10: 198 | F10: 0.8736 | G10: 0.4641 | H10: 11.02 | I10: 0.1686 | J10: 31.9 | K10: 32.18 | L10: 29.96 | M10: 0.2749 | N10: 0.0111
A11: MRAAY | B11: Murata Manufacturing Co | C11: 22.5 | D11: 81.6 | E11: 77.7 | F11: 2.178 | G11: 1.1781 | H11: 1743.35 | I11: 0.063 | J11: 25.22 | K11: N/A | L11: N/A | M11: 0.1773 | N11: 0.0089
B12: COMP AVG | C12: =AVERAGE(C8:C11) -> 267.4675 | D12: =AVERAGE(D8:D11) -> 621.65 | E12: =AVERAGE(E8:E11) -> 635.425 | F12: =AVERAGE(F8:F11) -> 1.11605 | G12: =AVERAGE(G8:G11) -> 0.557775 | H12: =AVERAGE(H8:H11) -> 466.7325 | I12: =AVERAGE(I8:I11) -> 0.108125 | J12: =AVERAGE(J8:J11) -> 32.935 | K12: =AVERAGE(K8:K10) -> 30.243333 | L12: =AVERAGE(L8:L11) -> 25.013333 | M12: =AVERAGE(M8:M11) -> 0.292875 | N12: =AVERAGE(N8:N11) -> 0.01045
B13: COMP MEDIAN | C13: =MEDIAN(C8:C11) -> 317.615 | D13: =MEDIAN(D8:D11) -> 222.5 | E13: =MEDIAN(E8:E11) -> 227 | F13: =MEDIAN(F8:F11) -> 0.83505 | G13: =MEDIAN(G8:G11) -> 0.4282 | H13: =MEDIAN(H8:H11) -> 56.28 | I13: =MEDIAN(I8:I11) -> 0.10045 | J13: =MEDIAN(J8:J11) -> 28.56 | ... N13: =MEDIAN(N8:N11) -> 0.01
A15: QRVO | B15: Qorvo Inc | C15: 106.43 | D15: 9.36 | E15: 9.7 | F15: -0.0461 | G15: -0.0461 | H15: 3.67 | I15: -0.013 | J15: 13.22x | K15: 16.3x | L15: 15.8x | M15: 0.128 | N15: 0
A19: Precedent Transaction Analysis
A20: Date | B20: Seller | C20: Acquirer | F20: Terms | I20: Multiple
A21: 45252 | B21: Vmware | C21: Broadcomm | F21: $84.2b | I21: ~14x
A22: 45938 | B22: Qorvo | C22: Skyworks | F22: $22b | I22: 10.5x

Sheet Valuation
A1: Qorvo Inc. (NYSE: QRVO)
A2: Share Price (as of 5/24/26) | B2: 106.43
A3: Shares Out. | B3: 88.01M
A4: Market Cap | B4: 9370000
A5: Cash | B5: =DCF!C38 -> 1021176
A6: Debt | B6: =DCF!C39 -> 1549215
A7: TEV | B7: =(B4-B5)+B6 -> 9898039
A8: FY24 EBITDA | B8: =DCF!F8 -> 506604
A9: EV / FY24 EBITDA | B9: =(B7/B8) -> 19.53802
A11: Base Case Valuation Summary:
A12: FY27 EBITDA: | B12: =DCF!H8 -> 791017.02
A13: Target Multiple | B13: 13
A14: EV | B14: =B12*B13 -> 10283221
A15: Net Debt | B15: =(Model!S104+Model!S100)-Model!S78 -> 486783.49
A16: Market Cap | B16: =(B14-B15) -> 9796437.8
A17: Shares Out. | B17: =Model!S64 -> 92300
A18: 3-Year Price Target | B18: =B16/B17 -> 106.13692
A19: Total Return: | B19: =B18/(B2-1) -> 1.0067051
A20: IRR | B20: =(1+B19)^(1/3)-1 -> 0.26132747
A22: DCF Valuation | B22: =DCF!C43 -> 107.09829
A23: Total Return: | B23: =B22/(B2-1) -> 1.0158237
A24: IRR | B24: =(1+B23)^(1/3)-1 -> 0.2632351
A26: Blended PT: | B26: =AVERAGE(B22,B18) -> 101.55877
A27: Total Return: | B27: =B26/(B2-1) -> 0.96328148
A28: IRR | B28: =(1+B27)^(1/3)-1 -> 0.25216297

Sheet Scenario
B1: Base | C1: Bull | D1: Bear
B2: FY2027 | C2: FY2027 | D2: FY2027
A3: Revenue | B3: =Model!AA4 -> 4429354 | C3: =Model!AB4 -> 4650821.7 | D3: =Model!AC4 -> 4296473.3
A4: 3yr Growth | B4: =(Model!AA4-Model!Q$4)/Model!Q$4 -> 0.191016 | C4: =(Model!AB4-Model!Q$4)/Model!Q$4 -> 0.2505668 | D4: =(Model!AC4-Model!Q$4)/Model!Q$4 -> 0.15528552
A6: Adj. EBITDA | B6: =Model!AA52 -> 667961.56 | C6: =Model!AB52 -> 930164.33 | D6: =Model!AC52 -> 386682.6
A7: Margin | B7: =B6/B$3 -> 0.15080338 | C7: =C6/C$3 -> 0.2 | D7: =D6/D$3 -> 0.09
A9: FCF | B9: =Model!AA176+Model!AA184 -> 1127323.1 | C9: =Model!AB176+Model!AB184 -> 1555928.9 | D9: =Model!AC176+Model!AC184 -> 852790.39
A10: Margin | B10: =B9/B3 -> 0.25451186 | C10: =C9/C3 -> 0.33454925 | D10: =D9/D3 -> 0.19848614
A11: Conversion | B11: =B9/B6 -> 1.6877066 | C11: =C9/C6 -> 1.6727463 | D11: =D9/D6 -> 2.2054015
A13: EBITDA Multiple | B13: 12 | C13: 15 | D13: 10
A14: EV | B14: =B13*B6 -> 8015538.7 | C14: =C13*C6 -> 13952465 | D14: =D13*D6 -> 3866826
A15: Net Debt | B15: =(Model!AA100+Model!AA104)-Model!AA78 -> 465534.86 | C15: =(Model!AB100+Model!AB104)-Model!AB78 -> 422187.65 | D15: =(Model!AC100+Model!AC104)-Model!AC78 -> 519718.87
A16: Equity Value | B16: =B14-B15 -> 7550003.9 | C16: =C14-C15 -> 13530277 | D16: =D14-D15 -> 3347107.1
A17: Sh. Out. | B17: =Model!AA63 -> 91000 | C17: =Model!AB63 -> 88270 | D17: =Model!AC63 -> 91910
A18: Price Target | B18: =B16/B17 -> 82.967076 | C18: =C16/C17 -> 153.28285 | D18: =D16/D17 -> 36.417225
A20: Upside/Downside | B20: =B18/Valuation!B$2-1 -> -0.22045405 | C20: =C18/Valuation!B$2-1 -> 0.44022223 | D20: =D18/Valuation!B$2-1 -> -0.65782932
A21: IRR | B21: =(1+B20)^(1/3)-1 -> -0.079662241 | C21: =(1+C20)^(1/3)-1 -> 0.12930132 | D21: =(1+D20)^(1/3)-1 -> -0.30056462
A22: Risk/Reward vs Bear Case | B22: =B20/$D$20 -> 0.33512347 | C22: =C20/$D$20 -> -0.66920432

Sheet Model Summary
B1: =Model!N2 -> 2022 | C1: =Model!O2 -> 2023 | D1: =Model!P2 -> 2024 | E1: =Model!Q2 -> 2025 | F1: =Model!R2 -> 2026 | G1: =Model!S2 -> 2027 | H1: =Model!T2 -> 2028 | I1: =Model!U2 -> 2029 | J1: =Model!V2 -> 2030
A2: Revenue | B2: =Model!N4 -> 4645714 | C2: =Model!O4 -> 3569399 | D2: =Model!P4 -> 3769506 | E2: =Model!Q4 -> 3718971 | F2: =Model!R4 -> 3942109.3 | G2: =Model!S4 -> 4178635.8 | H2: =Model!T4 -> 4429354 | I2: =Model!U4 -> 4695115.2 | J2: =Model!V4 -> 4976822.1
A3: Growth | C3: =DCF!D6 -> -0.23167913 | D3: =DCF!E6 -> 0.056061819 | E3: =DCF!F6 -> -0.013406266 | F3: =DCF!G6 -> 0.06 | G3: =DCF!H6 -> 0.06 | H3: =DCF!I6 -> 0.06 | I3: =DCF!J6 -> 0.06 | J3: =DCF!K6 -> 0.06
A5: Gross Profit | B5: =Model!N6 -> 2286168 | C5: =Model!O6 -> 1296942 | D5: =Model!P6 -> 1488495 | E5: =Model!Q6 -> 1535589 | F5: =Model!R6 -> 1773949.2 | G5: =Model!S6 -> 1880386.1 | H5: =Model!T6 -> 1993209.3 | I5: =Model!U6 -> 2112801.8 | J5: =Model!V6 -> 2239570
A6: Margin | B6: =B$5/B2 -> 0.49210261 | C6: =C$5/C2 -> 0.36335024 | D6: =D$5/D2 -> 0.394878 | E6: =E$5/E2 -> 0.41290696 | F6: =F$5/F2 -> 0.45 | G6: =G$5/G2 -> 0.45 | H6: =H$5/H2 -> 0.45 | I6: =I$5/I2 -> 0.45 | J6: =J$5/J2 -> 0.45
A8: SG&A | B8: =Model!N10 -> 349718 | C8: =Model!O10 -> 358790 | D8: =Model!P10 -> 389140 | E8: =Model!Q10 -> 403624 | F8: =Model!R10 -> 394210.93 | G8: =Model!S10 -> 406037.25 | H8: =Model!T10 -> 418218.37 | I8: =Model!U10 -> 430764.92 | J8: =Model!V10 -> 443687.87
A9: Margin | B9: =B$8/B2 -> 0.075277557 | C9: =C$8/C2 -> 0.10051832 | D9: =D$8/D2 -> 0.10323369 | E9: =E$8/E2 -> 0.1085311 | F9: =F$8/F2 -> 0.1 | G9: =G$8/G2 -> 0.097169811 | H9: =H$8/H2 -> 0.094419722 | I9: =I$8/I2 -> 0.091747466 | J9: =J$8/J2 -> 0.08915084
A11: EBITDA | B11: =DCF!C8 -> 1524158 | C11: =DCF!D8 -> 453553 | D11: =DCF!E8 -> 668794 | E11: =DCF!F8 -> 506604 | F11: =702484 -> 702484 | G11: =DCF!H8 -> 791017.02 | H11: =DCF!I8 -> 831665.62 | I11: =DCF!J8 -> 875664.85 | J11: =DCF!K8 -> 923213.74
A12: Margin | B12: =B$11/B2 -> 0.32807831 | C12: =C$11/C2 -> 0.12706705 | D12: =D$11/D2 -> 0.17742219 | E12: =E$11/E2 -> 0.13622155 | F12: =F$11/F2 -> 0.17820003 | G12: =G$11/G2 -> 0.1893003 | H12: =H$11/H2 -> 0.18776228 | I12: =I$11/I2 -> 0.18650551 | J12: =J$11/J2 -> 0.18550266
A14: D&A | B14: =Model!N158+Model!N159 -> 361415 | C14: =Model!O158+Model!O159 -> 338848 | D14: =Model!P158+Model!P159 -> 320933 | E14: =Model!Q158+Model!Q159 -> 296836 | F14: =Model!R158+Model!R159 -> 290603.2 | G14: =Model!S158+Model!S159 -> 284530.66 | H14: =Model!T158+Model!T159 -> 278613.84 | I14: =Model!U158+Model!U159 -> 272848.34 | J14: =Model!V158+Model!V159 -> 267229.87
A15: Margin | B15: =B$14/B2 -> 0.077795361 | C15: =C$14/C2 -> 0.094931388 | D15: =D$14/D2 -> 0.085139273 | E15: =E$14/E2 -> 0.079816702 | F15: =F$14/F2 -> 0.073717693 | G15: =G$14/G2 -> 0.068091759 | H15: =H$14/H2 -> 0.062901688 | I15: =I$14/I2 -> 0.058113236 | J15: =J$14/J2 -> 0.053694881
A17: Operating Income | B17: =Model!M14 -> 906627 | C17: =Model!N14 -> 1226069 | D17: =Model!O14 -> 183168 | E17: =Model!P14 -> 417106 | F17: =Model!Q14 -> 288096 | G17: =Model!R14 -> 906627 | H17: =Model!S14 -> 586388.75 | I17: =Model!T14 -> 633753.2 | J17: =Model!U14 -> 684324.94
A18: Margin | B18: =B$17/B2 -> 0.19515343 | C18: =C$17/C2 -> 0.34349452 | D18: =D$17/D2 -> 0.048592044 | E18: =E$17/E2 -> 0.11215629 | F18: =F$17/F2 -> 0.073081688 | G18: =G$17/G2 -> 0.19515343 | H18: =H$17/H2 -> 0.13238697 | I18: =I$17/I2 -> 0.13498139 | J18: =J$17/J2 -> 0.13750239
A20: Interest Expense | B20: =Model!N16 -> -63326 | C20: =Model!O16 -> -68463 | D20: =Model!P16 -> -69245 | E20: =Model!Q16 -> -78328 | F20: =Model!R16 -> -79111.28 | G20: =Model!S16 -> -79902.393 | H20: =Model!T16 -> -80701.417 | I20: =Model!U16 -> -81508.431 | J20: =Model!V16 -> -82323.515
A21: EBT | B21: =Model!N21 -> 1,181,084 | C21: =Model!O21 -> 124629 | D21: =Model!P21 -> 73560 | E21: =Model!Q21 -> 65899 | F21: 411880.9 | G21: =Model!S21 -> 506486.36 | H21: =Model!T21 -> 553051.78 | I21: =Model!U21 -> 602816.51 | J21: =Model!V21 -> 655983.87
A23: Tax | B23: -147731 | C23: =Model!O23 -> -21477 | D23: =Model!P23 -> -143882 | E23: =Model!Q23 -> -10284 | F23: -90613.8 | G23: =Model!S23 -> -111427 | H23: =Model!T23 -> -121671.39 | I23: =Model!U23 -> -132619.63 | J23: =Model!V23 -> -144316.45
A24: Net Income | B24: 1033353 | C24: =Model!O24 -> 103152 | D24: =Model!P24 -> -70322 | E24: =Model!Q24 -> 55615 | F24: 321267.08 | G24: =Model!S24 -> 395059.36 | H24: =Model!T24 -> 431380.39 | I24: =Model!U24 -> 470196.88 | J24: =Model!V24 -> 511667.42
A26: Sh. Out. | B26: 92915 | C26: 98736 | D26: =Model!P63 -> 97,557 | E26: =Model!Q63 -> 94920 | F26: =Model!R63 -> 93800 | G26: =Model!S63 -> 92300 | H26: =Model!T63 -> 91000 | I26: =Model!U63 -> 89500 | J26: =Model!V63 -> 88000
A27: EPS | B27: =Model!N57 -> 9.26 | C27: =Model!O57 -> 1 | D27: =Model!P57 -> -0.72 | E27: =Model!Q57 -> 0.6 | F27: =Model!R57 -> 1.55 | G27: =Model!S57 -> 3.2 | H27: =Model!T57 -> 4.15 | I27: =Model!U57 -> 4.65 | J27: =Model!V57 -> 5.1
A29: FCF | B29: =DCF!C25 -> 1076797.8 | C29: =DCF!D25 -> 22059.04 | D29: =DCF!E25 -> 343935.68 | E29: =DCF!F25 -> 552887.88 | F29: 561737 | G29: =DCF!H25 -> 630760.23 | H29: =DCF!I25 -> 662451.09 | I29: =DCF!J25 -> 696775.24 | J29: =DCF!K25 -> 733890.2
A31: Net Leverage | B31: =(Model!N104-Model!N78)/Model!N52 -> 0.70498334 | C31: =(Model!O104-Model!O78)/Model!O52 -> 2.7324613 | D31: =(Model!P104-Model!P78)/Model!P52 -> 0.77753987 | E31: =(Model!Q104-Model!Q78)/Model!Q52 -> 1.0423112 | F31: =0.72 -> 0.72 | G31: =(Model!S104-Model!S78)/Model!S52 -> 0.6153894 | H31: =(Model!T104-Model!T78)/Model!T52 -> 0.55976206 | I31: =(Model!U104-Model!U78)/Model!U52 -> 0.50688486 | J31: =(Model!V104-Model!V78)/Model!V52 -> 0.45683265

Sheet Share Price
A2: Date | B2: Share Price History
A3: 46169 | B3: 104.2
A4: 46168 | B4: 108.23
A5: 46164 | B5: 106.43
A6: 46163 | B6: 97.74
A7: 46162 | B7: 98.78
A8: 46161 | B8: 94.57
A9: 46160 | B9: 94.21
A10: 46157 | B10: 92.25
A11: 46156 | B11: 90.46
A12: 46155 | B12: 91.51
A13: 46154 | B13: 89.73
A14: 46153 | B14: 93.41
... A2868: 42006 | B2868: 70.4
