Workbook
Name IQ_CH: 110000
Name IQ_CQ: 5000
Name IQ_CY: 10000
Name IQ_DAILY: 500000
Name IQ_FH: 100000
Name IQ_FQ: 500
Name IQ_FY: 1000
Name IQ_LTM: 2000
Name IQ_MONTH: 15000
Name IQ_NTM: 6000
Name IQ_WEEK: 50000
Name IQ_YTD: 3000

Sheet Introduction
C7: Key:
C8: Linked Cell - No Action Required: | D8: Black
C9: Hard Input - No Action Required: | D9: Blue
C10: Empty - Action Required:
C11: Complete - Correct Output | D11: Y
C12: Complete - Incorrect Output | D12: Y
C14: Analyst Actions:
C15: You will be scored based on the following: - Correct cell output - Correct use of formulas (don't hardcode) - Speed (make sure you submit before the time limit) (Make sure to focus more on accuracy and quality, rather than speed) - You will need to refer to the videos to support your working through the valuation model. - You will only be able to take this simulation once. Make sure you have charge on your laptop and a fully functioning Microsoft Excel. If you do require any support please email massupport@amplifyme.com or your course facilitator.
XX1000: 66258

Sheet Income Statement Assumptions
C2: Tesla Inc
C3: TSLA
A5: Task 1 | C5: Revenue Assumptions
C7: Option 1: Historic Growth Rate
C9: One way to forecast revenue is to project revenue using historic revenue growth. You will need to calculate revenue growth rate between 2024 and 2025, decreasing this % growth rate by 2% per year to 2030.
C12: Option 2: Market Growth Rate
C14: The second way to forecast revenue is to use market data to project future revenue growth. You will be able to extrapolate revenue growth using the following:
C15: Tesla current market share: | H15: 0.12 | J15: Source: Visual Capitalist
C16: EV market share growth 5-year CAGR | H16: 0.14 | J16: Source: Statista
C17: Tesla annual growth in market share | I17: =I37 -> 2026 | J17: =I17+1 -> 2027 | K17: =J17+1 -> 2028 | L17: =K17+1 -> 2029 | M17: =L17+1 -> 2030
I18: -0.08 | J18: -0.05 | K18: -0.03 | L18: 0 | M18: 0.02 | N18: E.g. 19.9% * 1.08
C21: Option 3: Research Forecasts
I24: =I17 -> 2026 | J24: =I24+1 -> 2027 | K24: =J24+1 -> 2028 | L24: =K24+1 -> 2029 | M24: =L24+1 -> 2030
H25: JP Morgan | I25: 0.204 | J25: 0.245 | K25: 0.283 | L25: 0.421 | M25: 0.35
H26: Bank of America | I26: 0.1589 | J26: 0.1245 | K26: 0.1012 | L26: 0.0865 | M26: 0.07
H27: Deutsche Bank | I27: 0.153 | J27: 0.164 | K27: 0.175 | L27: 0.186 | M27: 0.16
H28: Citi | I28: 0.167 | J28: 0.14 | K28: 0.12 | L28: 0.1 | M28: 0.09
H29: Goldman Sachs | I29: 0.134 | J29: 0.14 | K29: 0.152 | L29: 0.162 | M29: 0.14
H30: Average | I30: =AVERAGE(I25:I29) -> 0.16338 | J30: =AVERAGE(J25:J29) -> 0.1627 | K30: =AVERAGE(K25:K29) -> 0.16624 | L30: =AVERAGE(L25:L29) -> 0.1911 | M30: =AVERAGE(M25:M29) -> 0.162
C33: Revenue Assumptions Recap:
C36: Income Statement | I36: Projected
G37: Units | H37: 2025 | I37: =H37+1 -> 2026 | J37: =I37+1 -> 2027 | K37: =J37+1 -> 2028 | L37: =K37+1 -> 2029 | M37: =L37+1 -> 2030 | O37: -
C38: Historic Growth Rate | G38: % | H38: =('Simple Operating Model'!I10/'Simple Operating Model'!H10)-1 -> -0.029306992 | I38: =H38-0.02 -> -0.049306992 | J38: =I38-0.02 -> -0.069306992 | K38: =J38-0.02 -> -0.089306992 | L38: =K38-0.02 -> -0.10930699 | M38: =L38-0.02 -> -0.12930699 | O38: =C38 -> Historic Growth Rate
C39: Market Revenue | H39: ='Simple Operating Model'!I10 -> 94827 | I39: =(H39/$H$15)*(1+$H$16)*($H$15*(1+I18)) -> 99454.558 | J39: =(I39/$H$15)*(1+$H$16)*($H$15*(1+J18)) -> 107709.29 | K39: =(J39/$H$15)*(1+$H$16)*($H$15*(1+K18)) -> 119104.93 | L39: =(K39/$H$15)*(1+$H$16)*($H$15*(1+L18)) -> 135779.62 | M39: =(L39/$H$15)*(1+$H$16)*($H$15*(1+M18)) -> 157884.54 | O39: =C40 -> Market Growth Rate
C40: Market Growth Rate | I40: =(I39/H39)-1 -> 0.0488 | J40: =(J39/I39)-1 -> 0.083 | K40: =(K39/J39)-1 -> 0.1058 | L40: =(L39/K39)-1 -> 0.14 | M40: =(M39/L39)-1 -> 0.1628 | O40: =C41 -> Research Forecasts
C41: Research Forecasts | I41: =I30 -> 0.16338 | J41: =J30 -> 0.1627 | K41: =K30 -> 0.16624 | L41: =L30 -> 0.1911 | M41: =M30 -> 0.162
C44: Pick your preferred assumption!
C46: Option chosen: | E46: Research Forecasts | H46: Justification: | J46: It was the most familiar to me
C47: (no red/green conditional formatting)
XX999: 66258

Sheet Simple Operating Model
C2: Tesla Inc
C3: TSLA
A5: Task 2 | C5: Income Statement
C7: Income Statement | J7: Projected
C8: Amounts in millions | G8: Units | H8: =I8-1 -> 2024 | I8: 2025 | J8: =I8+1 -> 2026 | K8: =J8+1 -> 2027 | L8: =K8+1 -> 2028 | M8: =L8+1 -> 2029 | N8: =M8+1 -> 2030
C10: Revenue | G10: $m | H10: 97690 | I10: 94827 | J10: =I10*(1+J33) -> 110319.84 | K10: =J10*(1+K33) -> 128268.87 | L10: =K10*(1+L33) -> 149592.29 | M10: =L10*(1+M33) -> 178179.38 | N10: =M10*(1+N33) -> 207044.44
C11: Cost of Sales | G11: $m | H11: 80240 | I11: 77733 | J11: =J10*J34 -> 90433.018 | K11: =K10*K34 -> 102910.27 | L11: =L10*L34 -> 117410.12 | M11: =M10*M34 -> 136740.86 | N11: =N10*N34 -> 155283.33
C12: Gross Profit | G12: $m | H12: 17450 | I12: =I10-I11 -> 17094 | J12: =J10-J11 -> 19886.818 | K12: =K10-K11 -> 25358.607 | L12: =L10-L11 -> 32182.172 | M12: =M10-M11 -> 41438.514 | N12: =N10-N11 -> 51761.109
C14: Product Development | G14: $m | H14: 4540 | I14: 6411 | J14: =J35*J10 -> 4412.7934 | K14: =K35*K10 -> 5130.7549 | L14: =L35*L10 -> 5983.6916 | M14: =M35*M10 -> 7127.1751 | N14: =N35*N10 -> 6211.3331
C15: Selling, General & Administrative | G15: $m | H15: 5150 | I15: 5834 | J15: =J36*J10 -> 5515.9918 | K15: =K36*K10 -> 6092.7714 | L15: =L36*L10 -> 6731.653 | M15: =M36*M10 -> 7572.6235 | N15: =N36*N10 -> 8281.7774
C16: Restructuring and other | H16: 684 | I16: 494 | J16: 0 | K16: 0 | L16: 0 | M16: 0 | N16: 0
C17: Operating Income | G17: $m | H17: 7076 | I17: =I12-SUM(I14:I16) -> 4355 | J17: =J12-SUM(J14:J15) -> 9958.0325 | K17: =K12-SUM(K14:K15) -> 14135.08 | L17: =L12-SUM(L14:L15) -> 19466.827 | M17: =M12-SUM(M14:M15) -> 26738.716 | N17: =N12-SUM(N14:N15) -> 37267.998
C19: – Interest Income (Expense) | G19: $m | H19: 1219 | I19: 1342 | J19: 1137.5 | K19: 1421.875 | L19: 1777.3438 | M19: 2221.6797 | N19: 2777.0996
C20: – Other Income (Expense) | H20: 695 | I20: -419
C21: Pretax Income | G21: $m | H21: 8990 | I21: =SUM(I17:I20) -> 5278 | J21: =SUM(J17:J20) -> 11095.533 | K21: =SUM(K17:K20) -> 15556.955 | L21: =SUM(L17:L20) -> 21244.171 | M21: =SUM(M17:M20) -> 28960.396 | N21: =SUM(N17:N20) -> 40045.098
C22: – Tax Provision1 (Income) | G22: $m | H22: 1837 | I22: -1423 | J22: =-J38*J21 -> -2330.0618 | K22: =-K38*K21 -> -3266.9606 | L22: =-L38*L21 -> -4461.2759 | M22: =-M38*M21 -> -6081.6831 | N22: =-N38*N21 -> -8409.4706
C23: Net Income | G23: $m | H23: 7153 | I23: =SUM(I21:I22) -> 3855 | J23: =SUM(J21:J22) -> 8765.4707 | K23: =SUM(K21:K22) -> 12289.995 | L23: =SUM(L21:L22) -> 16782.895 | M23: =SUM(M21:M22) -> 22878.713 | N23: =SUM(N21:N22) -> 31635.627
C24: – Net (loss) income attributable to noncontrolling interests and redeemable noncontrolling interests in subsidiaries | G24: $m | H24: 62 | I24: -61 | J24: =-J40*J23 -> 0 | K24: =-K40*K23 -> 0 | L24: =-L40*L23 -> 0 | M24: =-M40*M23 -> 0 | N24: =-N40*N23 -> 0
C25: Net Income attributable to common stockholderes | G25: $m | H25: 7091 | I25: =SUM(I23:I24) -> 3794 | J25: =SUM(J23:J24) -> 8765.4707 | K25: =SUM(K23:K24) -> 12289.995 | L25: =SUM(L23:L24) -> 16782.895 | M25: =SUM(M23:M24) -> 22878.713 | N25: =SUM(N23:N24) -> 31635.627
C27: EBIT | G27: $m | H27: 7076 | I27: =I17 -> 4355 | J27: =J17 -> 9958.0325 | K27: =K17 -> 14135.08 | L27: =L17 -> 19466.827 | M27: =M17 -> 26738.716 | N27: =N17 -> 37267.998
C28: Depreciation & Amortization1 | G28: $m | H28: 5368 | I28: 6148 | J28: 6036 | K28: 8371 | L28: 11085 | M28: 13594 | N28: 17068
C29: EBITDA | G29: $m | H29: 12444 | I29: =SUM(I27:I28) -> 10503 | J29: =SUM(J27:J28) -> 15994.033 | K29: =SUM(K27:K28) -> 22506.08 | L29: =SUM(L27:L28) -> 30551.827 | M29: =SUM(M27:M28) -> 40332.716 | N29: =SUM(N27:N28) -> 54335.998
C31: Income Statement Drivers | G31: Units
H32: 0
C33: Revenue Growth | G33: % | H33: 0.0094757835 | I33: =I10/H10-1 -> -0.029306992 | J33: ='Income Statement Assumptions'!I41 -> 0.16338 | K33: ='Income Statement Assumptions'!J41 -> 0.1627 | L33: ='Income Statement Assumptions'!K41 -> 0.16624 | M33: ='Income Statement Assumptions'!L41 -> 0.1911 | N33: ='Income Statement Assumptions'!M41 -> 0.162 | P33: =(J33 - N33) / - 4 -> -0.000345
C34: Cost of Sales % Revenues | G34: % | H34: 0.82137373 | I34: =I11/I10 -> 0.81973489 | J34: =I34 -> 0.81973489 | K34: =J34 + $P34 -> 0.80230116 | L34: =K34 + $P34 -> 0.78486744 | M34: =L34 + $P34 -> 0.76743372 | N34: 0.75 | P34: =(J34 - N34) / - 4 -> -0.017433721
C35: Product Development as % Revenues | G35: % | H35: 0.04 | I35: =I14/I10 -> 0.067607327 | J35: 0.04 | K35: =J35 -> 0.04 | L35: =K35 -> 0.04 | M35: =L35 -> 0.04 | N35: 0.03 | P35: =(J35 - N35) / - 4 -> -0.0025
C36: Selling, General and Administrative Expenses % Revenues | G36: % | H36: 0.05 | I36: =I15/I10 -> 0.061522562 | J36: 0.05 | K36: =J36 + $P36 -> 0.0475 | L36: =K36 + $P36 -> 0.045 | M36: =L36 + $P36 -> 0.0425 | N36: 0.04 | P36: =(J36 - N36) / - 4 -> -0.0025
C37: D&A as a % of Revenue | G37: % | H37: 0.05494933 | I37: =I28/I10 -> 0.064833855 | J37: =J28/J10 -> 0.054713642 | K37: =K28/K10 -> 0.065261352 | L37: =L28/L10 -> 0.074101413 | M37: =M28/M10 -> 0.076293903 | N37: =N28/N10 -> 0.08243641
C38: Taxes % of Profit Before Tax | G38: % | H38: 0.08 | I38: =-I22/I21 -> 0.2696097 | J38: 0.21 | K38: =J38 -> 0.21 | L38: =K38 -> 0.21 | M38: =L38 -> 0.21 | N38: =M38 -> 0.21
C40: (1) Source: ValueInvesting.io
A42: Task 3 | C42: Discounted Cash Flow Analysis
C44: Weighted Average Cost of Capital
C46: Risk free rate (Rf) | F46: 0.0432 | G46: 1
C47: Equity Beta | F47: ='52 weeks share price data'!J14 -> 1.6339216 | G47: 2
C48: Equity risk premium (Rm - Rf) | F48: 0.0423 | G48: 3
C49: Cost of Equity (Ke) | F49: =F46+(F47*F48) -> 0.11231488
C51: Cost of debt | F51: 0.0445 | G51: 3
C52: Tax rate | F52: =J38 -> 0.21
C53: After-tax Cost of Debt (Kdt) | F53: =F51*(1-F52) -> 0.035155
C55: Percentage of Capital
C56: Debt | E56: 6736 | F56: =E56/E58 -> 0.0047933938
C57: Equity | E57: =G116 -> 1398531.4 | F57: =E57/E58 -> 0.99520661
C58: Total capital | E58: =SUM(E56:E57) -> 1405267.4 | F58: 1
C60: Weighted Average Cost of Capital | F60: =((F49*F57))+((F53*F56)) -> 0.11194502
C61: (1) As of April 28th, based on the current 10-year U.S. Treasury Bond Yield
C62: (2) TSLA 12m Daily Returns
C63: (3) Damodaran Implied ERP - start of 2026
C65: Discounted Cash Flow | J65: Projected
C66: Amounts in millions, except per share amount | G66: Units | H66: 2024 | I66: 2025 | J66: =$J$8 -> 2026 | K66: =$K$8 -> 2027 | L66: =$L$8 -> 2028 | M66: =$M$8 -> 2029 | N66: =$N$8 -> 2030
C68: EBIT | G68: $ | H68: =H27 -> 7076 | I68: =I27 -> 4355 | J68: =J27 -> 9958.0325 | K68: =K27 -> 14135.08 | L68: =L27 -> 19466.827 | M68: =M27 -> 26738.716 | N68: =N27 -> 37267.998
C69: ="Taxes @ "&TEXT(J38,"0.0%") -> Taxes @ 21.0% | G69: $ | H69: =- H68 * $J$38 -> -1485.96 | I69: =- I68 * $J$38 -> -914.55 | J69: =- J68 * $J$38 -> -2091.1868 | K69: =- K68 * $J$38 -> -2968.3669 | L69: =- L68 * $J$38 -> -4088.0337 | M69: =- M68 * $J$38 -> -5615.1303 | N69: =- N68 * $J$38 -> -7826.2797
C70: NOPAT | G70: $ | H70: =SUM(H68:H69) -> 5590.04 | I70: =SUM(I68:I69) -> 3440.45 | J70: =SUM(J68:J69) -> 7866.8457 | K70: =SUM(K68:K69) -> 11166.714 | L70: =SUM(L68:L69) -> 15378.793 | M70: =SUM(M68:M69) -> 21123.586 | N70: =SUM(N68:N69) -> 29441.719
C71: + Depreciation and Amortization | G71: $ | H71: =H28 -> 5368 | I71: =I28 -> 6148 | J71: =J28 -> 6036 | K71: =K28 -> 8371 | L71: =L28 -> 11085 | M71: =M28 -> 13594 | N71: =N28 -> 17068
C72: NWC | H72: 2703 | I72: 5570 | J72: 6513.7808 | K72: 7543.9545 | L72: 8731.7684 | M72: 10137.169 | N72: 12019.391
C73: ± Changes in working capital | G73: $ | H73: 0 | I73: =I72-H72 -> 2867 | J73: =J72-I72 -> 943.7808 | K73: =K72-J72 -> 1030.1737 | L73: =L72-K72 -> 1187.814 | M73: =M72-L72 -> 1405.4007 | N73: =N72-M72 -> 1882.2218
C74: – Capital expenditures | G74: $ | H74: -9949 | I74: -11339 | J74: =J84*-J10 -> -12804.961 | K74: =K84*-K10 -> -14888.328 | L74: =L84*-L10 -> -17363.363 | M74: =M84*-M10 -> -20681.502 | N74: =N84*-N10 -> -24031.906
C75: Unlevered Free Cash Flows | G75: $ | H75: =H70+H71+H73+H74 -> 1009.04 | I75: =I70+I71+I73+I74 -> 1116.45 | J75: =J70+J71+J73+J74 -> 2041.6658 | K75: =K70+K71+K73+K74 -> 5679.5594 | L75: =L70+L71+L73+L74 -> 10288.244 | M75: =M70+M71+M73+M74 -> 15441.484 | N75: =N70+N71+N73+N74 -> 24360.035
C77: Discount rate | G77: % | J77: =$F$60 -> 0.11194502 | K77: =$F$60 -> 0.11194502 | L77: =$F$60 -> 0.11194502 | M77: =$F$60 -> 0.11194502 | N77: =$F$60 -> 0.11194502
C78: Discount period | G78: # | J78: 1 | K78: =J78+1 -> 2 | L78: =K78+1 -> 3 | M78: =L78+1 -> 4 | N78: =M78+1 -> 5
C79: Discount factor | G79: # | J79: =1/(1+J77)^J78 -> 0.89932504 | K79: =1/(1+K77)^K78 -> 0.80878552 | L79: =1/(1+L77)^L78 -> 0.72736107 | M79: =1/(1+M77)^M78 -> 0.65413402 | N79: =1/(1+N77)^N78 -> 0.5882791
C81: Present Value of Unlevered Free Cash Flow | G81: $ | J81: =J75*J79 -> 1836.1212 | K81: =K75*K79 -> 4593.5454 | L81: =L75*L79 -> 7483.2682 | M81: =M75*M79 -> 10100.8 | N81: =N75*N79 -> 14330.499
C83: DCF Drivers | G83: Units
C84: Capex as a % of Revenue | G84: % | H84: 0.091947134 | I84: 0.11607125 | J84: =I84 -> 0.11607125 | K84: =J84 -> 0.11607125 | L84: =K84 -> 0.11607125 | M84: =L84 -> 0.11607125 | N84: =M84 -> 0.11607125
C85: Inventory | H85: 12017 | I85: 13626 | J85: =J86*J11 -> 15356.933 | K85: =K86*K11 -> 17475.764 | L85: =L86*L11 -> 19938.064 | M85: =M86*M11 -> 23220.725 | N85: =N86*N11 -> 26369.524
C86: Inventory as % of COGS | H86: 0.15189665 | I86: 0.16981555 | J86: =I86 -> 0.16981555 | K86: =J86 -> 0.16981555 | L86: =K86 -> 0.16981555 | M86: =L86 -> 0.16981555 | N86: =M86 -> 0.16981555
C87: Trade Receivables | H87: 3508 | I87: 4418 | J87: =J88*J10 -> 4989.1804 | K87: =K88*K10 -> 5800.92 | L87: =L88*L10 -> 6765.265 | M87: =M88*M10 -> 8058.1071 | N87: =N88*N10 -> 9363.5205
C88: Trade Receievables % of revenue | H88: 0.03624978 | I88: 0.04522469 | J88: =I88 -> 0.04522469 | K88: =J88 -> 0.04522469 | L88: =K88 -> 0.04522469 | M88: =L88 -> 0.04522469 | N88: =M88 -> 0.04522469
C89: Trade Payables | H89: -14431 | I89: -12474 | J89: =J90*-J11 -> -14058.592 | K89: =K90*-K11 -> -15998.288 | L89: =L90*-L11 -> -18252.415 | M89: =M90*-M11 -> -21257.546 | N89: =N90*-N11 -> -24140.132
C90: Trade Payables % of COGS | H90: 0.18240997 | I90: 0.15545862 | J90: =I90 -> 0.15545862 | K90: =J90 -> 0.15545862 | L90: =K90 -> 0.15545862 | M90: =L90 -> 0.15545862 | N90: =M90 -> 0.15545862
C92: DCF Value - Perpetuity Growth | I92: Terminal Value - Perpetuity Growth
I93: ="FY"&TEXT(N66,"0")&"E Unlevered Free Cash Flow" -> FY2030E Unlevered Free Cash Flow | L93: =N75 -> 24360.035
C94: ="NPV of UFCF "&TEXT(J66,"0")&" - "&TEXT(N66,"0") -> NPV of UFCF 2026 - 2030 | E94: =SUM(J81:N81) -> 38344.234 | I94: Perpetuity growth rate | L94: 0.03
C95: PV of Terminal Value | E95: =L95*N79 -> 180125.82 | I95: Terminal Value | L95: =(L93 * (1 + L94)) / (F60 - L94) -> 306191.08
C96: Implied Enterprise Value | E96: =SUM(E94:E95) -> 218470.05 | I96: Implied Exit Multiple | L96: =IFERROR(E95/(N29*N79),0) -> 5.6351423
C97: Less: Debt | E97: =-E56 -> -6736
C98: Add: Cash | E98: 16153 | G98: Implied Value Per Share | P98: Steps
C99: Add: Short Term Investments | E99: 27546 | I99: Perpetuity Growth Rate | O99: Perp. Growth | P99: 0.0025
C100: Implied Equity Value | E100: =SUM(E96:E99) -> 255433.05 | H100: =E102 -> 79.327034 | I100: =J100-$P$99 -> 0.025 | J100: =K100-$P$99 -> 0.0275 | K100: 0.03 | L100: =K100+$P$99 -> 0.0325 | M100: =L100+$P$99 -> 0.035
C101: Diluted shares | E101: 3220 | G101: WACC | H101: =H102-$P$101 -> 0.10694502 | O101: WACC | P101: 0.0025
C102: Implied Value Per Share | E102: =E100/E101 -> 79.327034 | H102: =H103-$P$101 -> 0.10944502
H103: ='Simple Operating Model'!F60 -> 0.11194502
H104: =H103+$P$101 -> 0.11444502
H105: =H104+$P$101 -> 0.11694502
C106: (1) Implied Shares Outstanding of common equity, assuming the conversion of all convertible subsidiary equity into common.
A109: Task 4 | C109: Enterprise Value Analysis
D111: Enterprise Value | I111: Enterprise Value Multiples | M111: Enterprise Value
D112: Amounts in millions as of 28 April 2026 | J112: LTM | K112: FY1 | M112: Amounts in millions as of April 28th 2026
D114: Share price | G114: 372.7 | I114: Revenue | J114: =I10 -> 94827 | K114: =J10 -> 110319.84 | M114: 52 Week High | N114: =MAX('52 weeks share price data'!$D$5:$D$256)*$G$115+$G$117-SUM($G$118:$G$119) -> 1801278.4 | O114: Max share price at close of day
D115: Diluted Shares | G115: =3752431984/1000000 -> 3752.432 | I115: EBITDA | J115: =I29 -> 10503 | K115: =J29 -> 15994.033 | M115: 52 Week Low | N115: =MIN('52 weeks share price data'!$D$5:$D$256)*$G$115+$G$117-SUM($G$118:$G$119) -> 996269.15 | O115: Min share price at close of day
D116: Equity Value | G116: =G114 * G115 -> 1398531.4 | I116: EV/Revenue | J116: =$G$120/J114 -> 14.358446 | K116: =$G$120/K114 -> 12.342009
D117: Total Debt | G117: =-E97 -> 6736 | I117: EV/EBITDA | J117: =$G$120/J115 -> 129.63614 | K117: =$G$120/K115 -> 85.129776
D118: Cash | G118: =E98 -> 16153 | I118: LTM = FY2025
D119: Cash Equivalents | G119: =E99 -> 27546
D120: Enterprise Value | G120: =G116+G117-SUM(G118:G119) -> 1361568.4
A123: Task 5 | C123: Trading Comparables
I125: Market | J125: Enterprise | K125: Enterprise Value / Revenue | M125: Enterprise Value / EBITDA
D126: Company | I126: Value | J126: Value | K126: LTM | L126: FY1 | M126: LTM | N126: FY1
D127: BYD | I127: 112346 | J127: 106838 | K127: 0.92 | L127: 0.72 | M127: 6.61 | N127: 5.05 | S127: There are three comps that you need to exclude from this list. The comps included in your high, mean, median and low calculations should be companies in the same industry (Autos) or wider industry infrastructure (EV charging/components).
D128: Rivian | I128: 18688 | J128: 21408 | K128: 3.05 | L128: 2.07 | M128: NA | N128: NA
...

Sheet CONDFORM 1
C2: Tesla Inc
C3: TSLA
A5: Task 1 | C5: Revenue Assumptions
C7: Option 1: Historic Growth Rate
C9: One way to forecast revenue is to project revenue using historic revenue growth. You will need to calculate revenue growth rate between 2022 and 2023, decreasing this % growth rate by 2% per year to 2028.
C12: Option 2: Market Growth Rate
C14: The second way to forecast revenue is to use market data to project future revenue growth. You will be able to extrapolate revenue growth using the following: | R14: Video 1
C15: Tesla current market share: | H15: 0.12 | J15: Source: Visual Capitalist
C16: EV market share growth 5-year CAGR | H16: 0.14 | J16: Source: Statista
C17: Tesla annual growth in market share | I17: =I37 -> 2024 | J17: =I17+1 -> 2025 | K17: =J17+1 -> 2026 | L17: =K17+1 -> 2027 | M17: =L17+1 -> 2028
I18: -0.08 | J18: -0.05 | K18: -0.03 | L18: 0 | M18: 0.02 | N18: E.g. 19.9% * 1.08
C21: Option 3: Broker forecasts
I24: =I17 -> 2024 | J24: =I24+1 -> 2025 | K24: =J24+1 -> 2026 | L24: =K24+1 -> 2027 | M24: =L24+1 -> 2028
H25: JP Morgan | I25: 0.204 | J25: 0.245 | K25: 0.283 | L25: 0.421 | M25: 0.35
H26: Bank of America | I26: 0.1589 | J26: 0.1245 | K26: 0.1012 | L26: 0.0865 | M26: 0.07
H27: Deutsche Bank | I27: 0.153 | J27: 0.164 | K27: 0.175 | L27: 0.186 | M27: 0.16
H28: Citi | I28: 0.167 | J28: 0.14 | K28: 0.12 | L28: 0.1 | M28: 0.09
H29: Goldman Sachs | I29: 0.134 | J29: 0.14 | K29: 0.152 | L29: 0.162 | M29: 0.14
H30: Average | I30: 0.16338 | J30: 0.1627 | K30: 0.16624 | L30: 0.1911 | M30: 0.162
C32: Option chosen: | E32: Broker Forecasts | H32: Justification:
C36: Income Statement | I36: Projected
G37: Units | H37: 2023 | I37: =H37+1 -> 2024 | J37: =I37+1 -> 2025 | K37: =J37+1 -> 2026 | L37: =K37+1 -> 2027 | M37: =L37+1 -> 2028 | P37: -
C38: Historic Growth Rate | G38: % | H38: ='Simple Operating Model'!I10/'Simple Operating Model'!H10-1 -> -0.029306992 | I38: =H38-2% -> -0.049306992 | J38: =I38-2% -> -0.069306992 | K38: =J38-2% -> -0.089306992 | L38: =K38-2% -> -0.10930699 | M38: =L38-2% -> -0.12930699 | P38: =C38 -> Historic Growth Rate
C39: Market Revenue | H39: ='Simple Operating Model'!I10 -> 94827 | I39: =(H39/$H$15)*(1+$H$16)*($H$15*(1+I18)) -> 99454.558 | J39: =(I39/'CONDFORM 1'!$H$15)*(1+$H$16)*($H$15*(1+J18)) -> 107709.29 | K39: =(J39/'CONDFORM 1'!$H$15)*(1+$H$16)*($H$15*(1+K18)) -> 119104.93 | L39: =(K39/'CONDFORM 1'!$H$15)*(1+$H$16)*($H$15*(1+L18)) -> 135779.62 | M39: =(L39/'CONDFORM 1'!$H$15)*(1+$H$16)*($H$15*(1+M18)) -> 157884.54 | P39: =C40 -> Market Growth Rate
C40: Market Growth Rate | I40: =I39/H39-1 -> 0.0488 | J40: =J39/I39-1 -> 0.083 | K40: =K39/J39-1 -> 0.1058 | L40: =L39/K39-1 -> 0.14 | M40: =M39/L39-1 -> 0.1628 | P40: =C41 -> Broker Forecasts
C41: Broker Forecasts | I41: =I30 -> 0.16338 | J41: =J30 -> 0.1627 | K41: =K30 -> 0.16624 | L41: =L30 -> 0.1911 | M41: =M30 -> 0.162

Sheet CONDFORM
C2: Tesla Inc
C3: TSLA
A5: Task 2 | C5: Income Statement
C7: Income Statement | J7: Projected
C8: Amounts in millions | G8: Units | H8: =I8-1 -> 2024 | I8: 2025 | J8: =I8+1 -> 2026 | K8: =J8+1 -> 2027 | L8: =K8+1 -> 2028 | M8: =L8+1 -> 2029 | N8: =M8+1 -> 2030
C10: Revenue | G10: $m | H10: 97690 | I10: 94827 | J10: =I10*(1+J33) -> 110319.84 | K10: =J10*(1+K33) -> 128268.87 | L10: =K10*(1+L33) -> 149592.29 | M10: =L10*(1+M33) -> 178179.38 | N10: =M10*(1+N33) -> 207044.44
C11: Cost of Sales | G11: $m | H11: 80240 | I11: 77733 | J11: =J10*J34 -> 90433.018 | K11: =K10*K34 -> 102910.27 | L11: =L10*L34 -> 117410.12 | M11: =M10*M34 -> 136740.86 | N11: =N10*N34 -> 155283.33
C12: Gross Profit | G12: $m | H12: 17450 | I12: =I10-I11 -> 17094 | J12: =J10-J11 -> 19886.818 | K12: =K10-K11 -> 25358.607 | L12: =L10-L11 -> 32182.172 | M12: =M10-M11 -> 41438.514 | N12: =N10-N11 -> 51761.109
C14: Product Development | G14: $m | H14: 4540 | I14: 6411 | J14: =J35*J10 -> 4412.7934 | K14: =K35*K10 -> 5130.7549 | L14: =L35*L10 -> 5983.6916 | M14: =M35*M10 -> 7127.1751 | N14: =N35*N10 -> 6211.3331
C15: Selling, General & Administrative | G15: $m | H15: 5150 | I15: 5834 | J15: =J36*J10 -> 5515.9918 | K15: =K36*K10 -> 6092.7714 | L15: =L36*L10 -> 6731.653 | M15: =M36*M10 -> 7572.6235 | N15: =N36*N10 -> 8281.7774
C16: Restructuring and other | H16: 684 | I16: 494 | J16: 0 | K16: 0 | L16: 0 | M16: 0 | N16: 0
C17: Operating Income | G17: $m | H17: 7076 | I17: =I12-SUM(I14:I16) -> 4355 | J17: =J12-SUM(J14:J15) -> 9958.0325 | K17: =K12-SUM(K14:K15) -> 14135.08 | L17: =L12-SUM(L14:L15) -> 19466.827 | M17: =M12-SUM(M13:M16) -> 26738.716 | N17: =N12-SUM(N14:N15) -> 37267.998
C19: – Interest Income (Expense) | G19: $m | H19: 1219 | I19: 1342 | J19: 1137.5 | K19: 1421.875 | L19: 1777.3438 | M19: 2221.6797 | N19: 2777.0996
C20: – Other Income (Expense) | H20: 695 | I20: -419
C21: Pretax Income | G21: $m | H21: 8990 | I21: =SUM(I17:I20) -> 5278 | J21: =SUM(J17:J20) -> 11095.533 | K21: =SUM(K17:K20) -> 15556.955 | L21: =SUM(L17:L20) -> 21244.171 | M21: =SUM(M17:M20) -> 28960.396 | N21: =SUM(N17:N20) -> 40045.098
C22: – Tax Provision1 (Income) | G22: $m | H22: 1837 | I22: -1423 | J22: =-J38*J21 -> -2330.0618 | K22: =-K38*K21 -> -3266.9606 | L22: =-L38*L21 -> -4461.2759 | M22: =-M38*M21 -> -6081.6831 | N22: =-N38*N21 -> -8409.4706
C23: Net Income | G23: $m | H23: 7153 | I23: =SUM(I21:I22) -> 3855 | J23: =SUM(J21:J22) -> 8765.4707 | K23: =SUM(K21:K22) -> 12289.995 | L23: =SUM(L21:L22) -> 16782.895 | M23: =SUM(M21:M22) -> 22878.713 | N23: =SUM(N21:N22) -> 31635.627
C24: – Net (loss) income attributable to noncontrolling interests and redeemable noncontrolling interests in subsidiaries | G24: $m | H24: 62 | I24: -61 | J24: =-J40*J23 -> 0 | K24: =-K40*K23 -> 0 | L24: =-L40*L23 -> 0 | M24: =-M40*M23 -> 0 | N24: =-N40*N23 -> 0
C25: Net Income attributable to common stockholderes | G25: $m | H25: 7091 | I25: =SUM(I23:I24) -> 3794 | J25: =SUM(J23:J24) -> 8765.4707 | K25: =SUM(K23:K24) -> 12289.995 | L25: =SUM(L23:L24) -> 16782.895 | M25: =SUM(M23:M24) -> 22878.713 | N25: =SUM(N23:N24) -> 31635.627
C27: EBIT | G27: $m | H27: 7076 | I27: =I17 -> 4355 | J27: =J17 -> 9958.0325 | K27: =K17 -> 14135.08 | L27: =L17 -> 19466.827 | M27: =M17 -> 26738.716 | N27: =N17 -> 37267.998
C28: Depreciation & Amortization1 | G28: $m | H28: 5368 | I28: 6148 | J28: 6036 | K28: 8371 | L28: 11085 | M28: 13594 | N28: 17068
C29: EBITDA | G29: $m | H29: 12444 | I29: =SUM(I27:I28) -> 10503 | J29: =SUM(J27:J28) -> 15994.033 | K29: =SUM(K27:K28) -> 22506.08 | L29: =SUM(L27:L28) -> 30551.827 | M29: =SUM(M27:M28) -> 40332.716 | N29: =SUM(N27:N28) -> 54335.998
A30: x
C31: Income Statement Drivers | G31: Units
H32: 0
C33: Revenue Growth | G33: % | H33: 0.0094757835 | I33: =I10/H10-1 -> -0.029306992 | J33: ='Income Statement Assumptions'!I41 -> 0.16338 | K33: ='Income Statement Assumptions'!J41 -> 0.1627 | L33: ='Income Statement Assumptions'!K41 -> 0.16624 | M33: ='Income Statement Assumptions'!L41 -> 0.1911 | N33: ='Income Statement Assumptions'!M41 -> 0.162 | P33: =(J33 - N33) / - 4 -> -0.000345
C34: Cost of Sales % Revenues | G34: % | H34: 0.82137373 | I34: =I11/I10 -> 0.81973489 | J34: =I34 -> 0.81973489 | K34: =J34 + $P34 -> 0.80230116 | L34: =K34 + $P34 -> 0.78486744 | M34: =L34 + $P34 -> 0.76743372 | N34: 0.75 | P34: =(J34 - N34) / - 4 -> -0.017433721
C35: Product Development as % Revenues | G35: % | H35: 0.04 | I35: =I14/I10 -> 0.067607327 | J35: 0.04 | K35: =J35 -> 0.04 | L35: =K35 -> 0.04 | M35: =L35 -> 0.04 | N35: 0.03 | P35: =(J35 - N35) / - 4 -> -0.0025
C36: Selling, General and Administrative Expenses % Revenues | G36: % | H36: 0.05 | I36: =I15/I10 -> 0.061522562 | J36: 0.05 | K36: =J36 + $P36 -> 0.0475 | L36: =K36 + $P36 -> 0.045 | M36: =L36 + $P36 -> 0.0425 | N36: 0.04 | P36: =(J36 - N36) / - 4 -> -0.0025
C37: D&A as a % of Revenue | G37: % | H37: 0.05494933 | I37: =I28/I10 -> 0.064833855 | J37: =J28/J10 -> 0.054713642 | K37: =K28/K10 -> 0.065261352 | L37: =L28/L10 -> 0.074101413 | M37: =M28/M10 -> 0.076293903 | N37: =N28/N10 -> 0.08243641
C38: Taxes % of Profit Before Tax | G38: % | H38: 0.08 | I38: =-I22/I21 -> 0.2696097 | J38: 0.21 | K38: =J38 -> 0.21 | L38: =K38 -> 0.21 | M38: =L38 -> 0.21 | N38: =M38 -> 0.21
C40: (1) Source: ValueInvesting.io
A42: Task 3 | C42: Discounted Cash Flow Analysis
C44: Weighted Average Cost of Capital
C46: Risk free rate (Rf) | F46: 0.0432 | G46: 1
C47: Equity Beta | F47: ='52 weeks share price data'!J14 -> 1.6339216 | G47: 2
C48: Equity risk premium (Rm - Rf) | F48: 0.0423 | G48: 3
C49: Cost of Equity (Ke) | F49: =F46+F47*F48 -> 0.11231488
C51: Cost of debt | F51: 0.0445 | G51: 3
C52: Tax rate | F52: =J38 -> 0.21
C53: After-tax Cost of Debt (Kdt) | F53: =F51*(1-F52) -> 0.035155
C55: Percentage of Capital
C56: Debt | E56: 6736 | F56: =E56/E58 -> 0.0047933938
C57: Equity | E57: =G116 -> 1398531.4 | F57: =E57/E58 -> 0.99520661
C58: Total capital | E58: =SUM(E56:E57) -> 1405267.4 | F58: 1
C60: Weighted Average Cost of Capital | F60: =F57*F49+F56*F53 -> 0.11194502
C61: (1) As of April 28th, based on the current 10-year U.S. Treasury Bond Yield
C62: (2) TSLA 12m Daily Returns
C63: (3) Damodaran Implied ERP - start of 2026
C65: Discounted Cash Flow | J65: Projected
C66: Amounts in millions, except per share amount | G66: Units | H66: 2023 | I66: 2024 | J66: =$J$8 -> 2026 | K66: =$K$8 -> 2027 | L66: =$L$8 -> 2028 | M66: =$M$8 -> 2029 | N66: =$N$8 -> 2030
C68: EBIT | G68: $ | H68: =H27 -> 7076 | I68: 7076 | J68: =J27 -> 9958.0325 | K68: =K27 -> 14135.08 | L68: =L27 -> 19466.827 | M68: =M27 -> 26738.716 | N68: =N27 -> 37267.998
C69: ="Taxes @ "&TEXT(J38,"0.0%") -> Taxes @ 21.0% | G69: $ | H69: =- H68 * $J$38 -> -1485.96 | I69: -778.36 | J69: =- J68 * $J$38 -> -2091.1868 | K69: =- K68 * $J$38 -> -2968.3669 | L69: =- L68 * $J$38 -> -4088.0337 | M69: =- M68 * $J$38 -> -5615.1303 | N69: =- N68 * $J$38 -> -7826.2797
C70: NOPAT | G70: $ | H70: =SUM(H68:H69) -> 5590.04 | I70: 6297.64 | J70: =SUM(J68:J69) -> 7866.8457 | K70: =SUM(K68:K69) -> 11166.714 | L70: =SUM(L68:L69) -> 15378.793 | M70: =SUM(M68:M69) -> 21123.586 | N70: =SUM(N68:N69) -> 29441.719
C71: + Depreciation and Amortization | G71: $ | H71: =H28 -> 5368 | I71: 5368 | J71: =J28 -> 6036 | K71: =K28 -> 8371 | L71: =L28 -> 11085 | M71: =M28 -> 13594 | N71: =N28 -> 17068
C72: NWC | H72: 2703 | I72: 5570 | J72: 6513.7808 | K72: 7543.9545 | L72: 8731.7684 | M72: 10137.169 | N72: 12019.391
C73: ± Changes in working capital | G73: $ | H73: 0 | I73: =I72-H72 -> 2867 | J73: =J72-I72 -> 943.7808 | K73: =K72-J72 -> 1030.1737 | L73: =L72-K72 -> 1187.814 | M73: =M72-L72 -> 1405.4007 | N73: =N72-M72 -> 1882.2218
C74: – Capital expenditures | G74: $ | H74: -9949 | I74: -11339 | J74: =J84*-J10 -> -12804.961 | K74: =K84*-K10 -> -14888.328 | L74: =L84*-L10 -> -17363.363 | M74: =M84*-M10 -> -20681.502 | N74: =N84*-N10 -> -24031.906
C75: Unlevered Free Cash Flows | G75: $ | H75: =H70+H71+H73+H74 -> 1009.04 | I75: =I70+I71+I73+I74 -> 3193.64 | J75: =J70+J71+J73+J74 -> 2041.6658 | K75: =K70+K71+K73+K74 -> 5679.5594 | L75: =L70+L71+L73+L74 -> 10288.244 | M75: =M70+M71+M73+M74 -> 15441.484 | N75: =N70+N71+N73+N74 -> 24360.035
C77: Discount rate | G77: % | J77: =$F$60 -> 0.11194502 | K77: =$F$60 -> 0.11194502 | L77: =$F$60 -> 0.11194502 | M77: =$F$60 -> 0.11194502 | N77: =$F$60 -> 0.11194502
C78: Discount period | G78: # | J78: 1 | K78: =J78+1 -> 2 | L78: =K78+1 -> 3 | M78: =L78+1 -> 4 | N78: =M78+1 -> 5
C79: Discount factor | G79: # | J79: =1/(1+J77)^J78 -> 0.89932504 | K79: =1/(1+K77)^K78 -> 0.80878552 | L79: =1/(1+L77)^L78 -> 0.72736107 | M79: =1/(1+M77)^M78 -> 0.65413402 | N79: =1/(1+N77)^N78 -> 0.5882791
C81: Present Value of Unlevered Free Cash Flow | G81: $ | J81: =J79*J75 -> 1836.1212 | K81: =K79*K75 -> 4593.5454 | L81: =L79*L75 -> 7483.2682 | M81: =M79*M75 -> 10100.8 | N81: =N79*N75 -> 14330.499
C83: DCF Drivers | G83: Units
C84: Capex as a % of Revenue | G84: % | H84: 0.091947134 | I84: 0.11607125 | J84: =I84 -> 0.11607125 | K84: =J84 -> 0.11607125 | L84: =K84 -> 0.11607125 | M84: =L84 -> 0.11607125 | N84: =M84 -> 0.11607125
C85: Inventory | H85: 12017 | I85: 13626 | J85: =J86*J11 -> 15356.933 | K85: =K86*K11 -> 17475.764 | L85: =L86*L11 -> 19938.064 | M85: =M86*M11 -> 23220.725 | N85: =N86*N11 -> 26369.524
C86: Inventory as % of COGS | H86: 0.15189665 | I86: 0.16981555 | J86: =I86 -> 0.16981555 | K86: =J86 -> 0.16981555 | L86: =K86 -> 0.16981555 | M86: =L86 -> 0.16981555 | N86: =M86 -> 0.16981555
C87: Trade Receivables | H87: 3508 | I87: 4418 | J87: =J88*J10 -> 4989.1804 | K87: =K88*K10 -> 5800.92 | L87: =L88*L10 -> 6765.265 | M87: =M88*M10 -> 8058.1071 | N87: =N88*N10 -> 9363.5205
C88: Trade Receievables % of revenue | H88: 0.03624978 | I88: 0.04522469 | J88: =I88 -> 0.04522469 | K88: =J88 -> 0.04522469 | L88: =K88 -> 0.04522469 | M88: =L88 -> 0.04522469 | N88: =M88 -> 0.04522469
C89: Trade Payables | H89: -14431 | I89: -12474 | J89: =J90*-J11 -> -14058.592 | K89: =K90*-K11 -> -15998.288 | L89: =L90*-L11 -> -18252.415 | M89: =M90*-M11 -> -21257.546 | N89: =N90*-N11 -> -24140.132
C90: Trade Payables % of COGS | H90: 0.18240997 | I90: 0.15545862 | J90: =I90 -> 0.15545862 | K90: =J90 -> 0.15545862 | L90: =K90 -> 0.15545862 | M90: =L90 -> 0.15545862 | N90: =M90 -> 0.15545862
C92: DCF Value - Perpetuity Growth | I92: Terminal Value - Perpetuity Growth | R92: 0.01
I93: ="FY"&TEXT(N66,"0")&"E Unlevered Free Cash Flow" -> FY2030E Unlevered Free Cash Flow | L93: =N75 -> 24360.035 | R93: 0.02
C94: ="NPV of UFCF "&TEXT(J66,"0")&" - "&TEXT(N66,"0") -> NPV of UFCF 2026 - 2030 | E94: =SUM(J81:N81) -> 38344.234 | I94: Perpetuity growth rate | L94: 0.03 | R94: 0.03
C95: PV of Terminal Value | E95: =L95*N79 -> 180125.82 | I95: Terminal Value | L95: =(L93 * (1 + L94)) / (F60 - L94) -> 306191.08 | R95: 0.04
C96: Implied Enterprise Value | E96: =SUM(E94:E95) -> 218470.05 | I96: Implied Exit Multiple | L96: =IFERROR(E95/(N29*N79),0) -> 5.6351423
C97: Less: Debt | E97: =-E56 -> -6736
C98: Add: Cash | E98: 16153 | G98: Implied Value Per Share | P98: Steps
C99: Add: Short Term Investments | E99: 27546 | I99: Perpetuity Growth Rate | O99: Perp. Growth | P99: 0.0025
C100: Implied Equity Value | E100: =SUM(E96:E99) -> 255433.05 | H100: =E102 -> 79.327034 | I100: =J100-$P$99 -> 0.025 | J100: =K100-$P$99 -> 0.0275 | K100: 0.03 | L100: =K100+$P$99 -> 0.0325 | M100: =L100+$P$99 -> 0.035
C101: Diluted shares | E101: 3220 | G101: WACC | H101: =H102-$P$101 -> 0.10694502 | I101: 80.529752 | J101: 82.464696 | K101: 84.525376 | L101: 86.724459 | M101: 89.076373 | O101: WACC | P101: 0.0025
C102: Implied Value Per Share | E102: =E100/E101 -> 79.327034 | H102: =H103-$P$101 -> 0.10944502 | I102: 78.121018 | J102: 79.925042 | K102: 81.842605 | L102: 83.884774 | M102: 86.064102
H103: 0.11194502 | I103: 75.854141 | J103: 77.53918 | K103: 79.327034 | L103: 81.22741 | M103: 83.251275
H104: =H103+$P$101 -> 0.11444502 | I104: 73.717185 | J104: 75.293803 | K104: 76.963773 | L104: 78.735639 | M104: 80.61902
H105: =H104+$P$101 -> 0.11694502 | I105: 71.699516 | J105: 73.177094 | K105: 74.739644 | L105: 76.394713 | M105: 78.150768
C106: (1) Implied Shares Outstanding of common equity, assuming the conversion of all convertible subsidiary equity into common.
A109: Task 4 | C109: Enterprise Value Analysis
D111: Enterprise Value | I111: Enterprise Value Multiples | M111: Enterprise Value
D112: Amounts in millions as of 28 April 2026 | J112: LTM | K112: FY1 | M112: Amounts in millions as of April 28th 2026
D114: Share price | G114: 372.7 | I114: Revenue | J114: =I10 -> 94827 | K114: =J10 -> 110319.84 | M114: 52 Week High | N114: 1801278.4 | O114: Max share price at close of day
D115: Diluted Shares | G115: =3752431984/1000000 -> 3752.432 | I115: EBITDA | J115: =I29 -> 10503 | K115: =J29 -> 15994.033 | M115: 52 Week Low | N115: 996269.15 | O115: Min share price at close of day
D116: Equity Value | G116: =G114 * G115 -> 1398531.4 | I116: EV/Revenue | J116: =$G$120/J114 -> 14.358446 | K116: =$G$120/K114 -> 12.342009
D117: Total Debt | G117: =-E97 -> 6736 | I117: EV/EBITDA | J117: =$G$120/J115 -> 129.63614 | K117: =$G$120/K115 -> 85.129776
D118: Cash | G118: =E98 -> 16153 | I118: LTM = FY2026
D119: Cash Equivalents | G119: =E99 -> 27546
D120: Enterprise Value | G120: =G116+G117-G118-G119 -> 1361568.4
A123: Task 5 | C123: Trading Comparables
I125: Market | J125: Enterprise | K125: Enterprise Value / Revenue | M125: Enterprise Value / EBITDA
D126: Company | I126: Value | J126: Value | K126: LTM | L126: FY1 | M126: LTM | N126: FY1
D127: BYD | I127: 112346 | J127: 106838 | K127: 0.92 | L127: 0.72 | M127: 6.61 | N127: 5.05
...

Sheet 52 weeks share price data
B2: Stock Beta (Tesla) - 12m Daily
B4: Number | C4: Date | D4: TSLA Close | E4: NASDAQ Close | F4: Return TSLA | G4: Return NASDAQ | I4: Results
B5: 1 | C5: 45775 | D5: 285.88 | E5: 472.41
B6: 2 | C6: 45776 | D6: 292.03 | E6: 475.53 | F6: =(D6-D5)/D5 -> 0.021512523 | G6: =(E6-E5)/E5 -> 0.0066044326 | I6: Method #1
B7: 3 | C7: 45777 | D7: 282.16 | E7: 475.47 | F7: =(D7-D6)/D6 -> -0.033797897 | G7: =(E7-E6)/E6 -> -0.000126175
B8: 4 | C8: 45778 | D8: 280.52 | E8: 481.68 | F8: =(D8-D7)/D7 -> -0.0058123051 | G8: =(E8-E7)/E7 -> 0.013060761 | I8: Covariance of Tesla & NASDAQ | J8: =_xlfn.COVARIANCE.S(F6:F256,G6:G256) -> 0.00017136054 | L8: =COVARIANCE.S(F6:F257,G6:G257)
B9: 5 | C9: 45779 | D9: 287.21 | E9: 488.83 | F9: =(D9-D8)/D8 -> 0.023848567 | G9: =(E9-E8)/E8 -> 0.01484388 | I9: Variance of NASDAQ | J9: =_xlfn.VAR.S(G6:G256) -> 0.00010487685 | L9: =VAR.S(G6:G257)
B10: 6 | C10: 45782 | D10: 280.26 | E10: 485.93 | F10: =(D10-D9)/D9 -> -0.024198322 | G10: =(E10-E9)/E9 -> -0.0059325328 | I10: TSLA Beta | J10: =J8/J9 -> 1.6339216 | L10: =J8/J9
B11: 7 | C11: 45783 | D11: 275.35 | E11: 481.41 | F11: =(D11-D10)/D10 -> -0.017519446 | G11: =(E11-E10)/E10 -> -0.0093017513
B12: 8 | C12: 45784 | D12: 276.22 | E12: 483.3 | F12: =(D12-D11)/D11 -> 0.003159615 | G12: =(E12-E11)/E11 -> 0.0039259675 | I12: Method #2
B13: 9 | C13: 45785 | D13: 284.82 | E13: 488.29 | F13: =(D13-D12)/D12 -> 0.031134603 | G13: =(E13-E12)/E12 -> 0.01032485
B14: 10 | C14: 45786 | D14: 298.26 | E14: 487.97 | F14: =(D14-D13)/D13 -> 0.047187697 | G14: =(E14-E13)/E13 -> -0.00065534826 | I14: =I10 -> TSLA Beta | J14: =SLOPE(F6:F256,G6:G256) -> 1.6339216 | L14: =SLOPE(F6:F257,G6:G257)
B15: 11 | C15: 45789 | D15: 318.38 | E15: 507.85 | F15: =(D15-D14)/D14 -> 0.067457923 | G15: =(E15-E14)/E14 -> 0.040740209
B16: 12 | C16: 45790 | D16: 334.07 | E16: 515.59 | F16: =(D16-D15)/D15 -> 0.049280734 | G16: =(E16-E15)/E15 -> 0.015240721
B17: 13 | C17: 45791 | D17: 347.68 | E17: 518.68 | F17: =(D17-D16)/D16 -> 0.040739965 | G17: =(E17-E16)/E16 -> 0.0059931341
B18: 14 | C18: 45792 | D18: 342.82 | E18: 519.25 | F18: =(D18-D17)/D17 -> -0.013978371 | G18: =(E18-E17)/E17 -> 0.0010989435
B19: 15 | C19: 45793 | D19: 349.98 | E19: 521.51 | F19: =(D19-D18)/D18 -> 0.020885596 | G19: =(E19-E18)/E18 -> 0.0043524314
B20: 16 | C20: 45796 | D20: 342.09 | E20: 522.01 | F20: =(D20-D19)/D19 -> -0.022544145 | G20: =(E20-E19)/E19 -> 0.00095875439
B21: 17 | C21: 45797 | D21: 343.82 | E21: 520.27 | F21: =(D21-D20)/D20 -> 0.0050571487 | G21: =(E21-E20)/E20 -> -0.0033332695
B22: 18 | C22: 45798 | D22: 334.62 | E22: 513.04 | F22: =(D22-D21)/D21 -> -0.026758187 | G22: =(E22-E21)/E21 -> -0.013896631
B23: 19 | C23: 45799 | D23: 341.04 | E23: 514 | F23: =(D23-D22)/D22 -> 0.019185942 | G23: =(E23-E22)/E22 -> 0.0018711991
B24: 20 | C24: 45800 | D24: 339.34 | E24: 509.24 | F24: =(D24-D23)/D23 -> -0.0049847525 | G24: =(E24-E23)/E23 -> -0.0092607004
B25: 21 | C25: 45804 | D25: 362.89 | E25: 521.22 | F25: =(D25-D24)/D24 -> 0.069399422 | G25: =(E25-E24)/E24 -> 0.023525253
B26: 22 | C26: 45805 | D26: 356.9 | E26: 518.91 | F26: =(D26-D25)/D25 -> -0.016506379 | G26: =(E26-E25)/E25 -> -0.0044319098
... B256: 252 | C256: 46140 | D256: 376.02 | E256: 657.55 | F256: =(D256-D255)/D255 -> -0.0069981778 | G256: =(E256-E255)/E255 -> -0.010056757

Sheet Grading
A1: WorksheetName | B1: Range | C1: Comparison | D1: Task
A2: Income Statement Assumptions | B2: I30:M30 | D2: 1
A3: Income Statement Assumptions | B3: H38:M38 | D3: 1
A4: Income Statement Assumptions | B4: I39:M39 | D4: 1
A5: Income Statement Assumptions | B5: I40:M40 | D5: 1
A6: Income Statement Assumptions | B6: I41:M41 | D6: 1
A7: Simple Operating Model | B7: L10 | D7: 2
A8: Simple Operating Model | B8: J15 | D8: 2
A9: Simple Operating Model | B9: M17 | D9: 2
A10: Simple Operating Model | B10: K22 | D10: 2
A11: Simple Operating Model | B11: L27 | D11: 2
A12: Simple Operating Model | B12: N29 | D12: 2
A13: Simple Operating Model | B13: F49 | D13: 3
... A23: Simple Operating Model | B23: H100 | D23: 3
A24: Simple Operating Model | B24: H103 | C24: CorrVal | D24: 3
A25: Simple Operating Model | B25: K100 | C25: CorrVal | D25: 3
A26: Simple Operating Model | B26: I101:M105 | C26: DataTable | D26: 3
A27: Simple Operating Model | B27: G120 | D27: 4
A28: Simple Operating Model | B28: J116:K116 | D28: 4
A29: Simple Operating Model | B29: J117:K117 | D29: 4
A30: Simple Operating Model | B30: N114 | D30: 4
A31: Simple Operating Model | B31: N115 | D31: 4
A32: Simple Operating Model | B32: K139:N139 | D32: 5
A33: Simple Operating Model | B33: K140:N140 | D33: 5
A34: Simple Operating Model | B34: K141:N141 | D34: 5
A35: Simple Operating Model | B35: K142:N142 | D35: 5
A36: Simple Operating Model | B36: F150 | D36: 6
A37: Simple Operating Model | B37: H150 | D37: 6
A38: Simple Operating Model | B38: F151 | D38: 6
... A47: Simple Operating Model | B47: H155 | D47: 6
